[{"firstName":"Carrie","lastName":"Schumm","tz":"658631734","mi":"603724496","clearance":"4","rnk":"rookie","nstype":"B","rld":"2016-06-18 00:00:00.0","hr":"ads5","birthday":"2011-05-22 00:00:00.0","sex":"F"},{"firstName":"Kelly","lastName":"Mraz","tz":"745900175","mi":"44784813","clearance":"6","rnk":"unknown","nstype":"F","rld":"2021-05-03 00:00:00.0","hr":"ads3","birthday":"2003-03-21 00:00:00.0","sex":"M"},{"firstName":"Oceane","lastName":"Waters","tz":"569787807","mi":"959974356","clearance":"7","rnk":"ultimate","nstype":"C","rld":"2020-02-28 00:00:00.0","hr":"ads6","birthday":"2018-01-11 00:00:00.0","sex":"M"},{"firstName":"Issac","lastName":"Pagac","tz":"514617232","mi":"626393799","clearance":"6","rnk":"champion","nstype":"G","rld":"2019-12-29 00:00:00.0","hr":"ads5","birthday":"1998-07-24 00:00:00.0","sex":"F"},{"firstName":"Eryn","lastName":"Kertzmann","tz":"136978715","mi":"524857929","clearance":"5","rnk":"unknown","nstype":"B","rld":"2022-08-27 00:00:00.0","hr":"ads2","birthday":"2007-11-06 00:00:00.0","sex":"M"},{"firstName":"Janessa","lastName":"Schuppe","tz":"824730766","mi":"615132132","clearance":"10","rnk":"champion","nstype":"E","rld":"2016-09-02 00:00:00.0","hr":"ads4","birthday":"2009-11-30 00:00:00.0","sex":"M"},{"firstName":"Jennie","lastName":"Fisher","tz":"405345950","mi":"77114520","clearance":"5","rnk":"rookie","nstype":"D","rld":"2015-06-06 00:00:00.0","hr":"ads4","birthday":"2017-07-14 00:00:00.0","sex":"M"},{"firstName":"Abdullah","lastName":"Johnson","tz":"802747030","mi":"429140756","clearance":"6","rnk":"mega","nstype":"F","rld":"2019-03-03 00:00:00.0","hr":"ads3","birthday":"2008-05-17 00:00:00.0","sex":"M"},{"firstName":"Isom","lastName":"Pacocha","tz":"932470073","mi":"405930316","clearance":"4","rnk":"unknown","nstype":"A","rld":"2024-12-28 00:00:00.0","hr":"ads2","birthday":"2002-09-08 00:00:00.0","sex":"F"},{"firstName":"Katarina","lastName":"Sanford","tz":"481589646","mi":"242293406","clearance":"2","rnk":"rookie","nstype":"B","rld":"2022-03-08 00:00:00.0","hr":"ads4","birthday":"1994-02-22 00:00:00.0","sex":"M"},{"firstName":"Tianna","lastName":"Crona","tz":"110967379","mi":"397660163","clearance":"5","rnk":"ultimate","nstype":"G","rld":"2023-09-05 00:00:00.0","hr":"ads1","birthday":"2000-11-06 00:00:00.0","sex":"F"},{"firstName":"Nova","lastName":"Pollich","tz":"777982216","mi":"119732197","clearance":"2","rnk":"champion","nstype":"F","rld":"2020-10-10 00:00:00.0","hr":"ads4","birthday":"2012-04-23 00:00:00.0","sex":"M"},{"firstName":"Paige","lastName":"Rath","tz":"395977259","mi":"595312112","clearance":"7","rnk":"mega","nstype":"D","rld":"2021-03-22 00:00:00.0","hr":"ads5","birthday":"2014-01-13 00:00:00.0","sex":"F"},{"firstName":"Gideon","lastName":"Gutkowski","tz":"262025133","mi":"408213218","clearance":"6","rnk":"mega","nstype":"D","rld":"2021-10-02 00:00:00.0","hr":"ads6","birthday":"2005-02-17 00:00:00.0","sex":"M"},{"firstName":"Natalie","lastName":"Lehner","tz":"607086766","mi":"966714267","clearance":"3","rnk":"mega","nstype":"G","rld":"2023-04-05 00:00:00.0","hr":"ads2","birthday":"2011-04-07 00:00:00.0","sex":"M"},{"firstName":"Kattie","lastName":"Kris","tz":"166391219","mi":"372915932","clearance":"0","rnk":"champion","nstype":"H","rld":"2022-05-15 00:00:00.0","hr":"ads1","birthday":"2004-07-03 00:00:00.0","sex":"M"},{"firstName":"Myriam","lastName":"Rolfson","tz":"621867092","mi":"771820179","clearance":"9","rnk":"rookie","nstype":"E","rld":"2021-09-25 00:00:00.0","hr":"ads2","birthday":"1994-03-08 00:00:00.0","sex":"M"},{"firstName":"Gisselle","lastName":"Effertz","tz":"414907923","mi":"716671536","clearance":"5","rnk":"mega","nstype":"H","rld":"2024-09-08 00:00:00.0","hr":"ads3","birthday":"2014-01-22 00:00:00.0","sex":"M"},{"firstName":"Jada","lastName":"Mosciski","tz":"951789809","mi":"18731988","clearance":"10","rnk":"rookie","nstype":"C","rld":"2019-03-20 00:00:00.0","hr":"ads6","birthday":"1994-09-30 00:00:00.0","sex":"F"},{"firstName":"Cali","lastName":"Erdman","tz":"759635642","mi":"311234730","clearance":"1","rnk":"champion","nstype":"H","rld":"2022-06-28 00:00:00.0","hr":"ads6","birthday":"2008-03-30 00:00:00.0","sex":"F"},{"firstName":"Quincy","lastName":"Feest","tz":"920673233","mi":"868379182","clearance":"3","rnk":"rookie","nstype":"C","rld":"2020-11-30 00:00:00.0","hr":"ads3","birthday":"2001-08-14 00:00:00.0","sex":"M"},{"firstName":"Raleigh","lastName":"Casper","tz":"275941177","mi":"397376128","clearance":"5","rnk":"ultimate","nstype":"A","rld":"2018-08-03 00:00:00.0","hr":"ads3","birthday":"2019-03-31 00:00:00.0","sex":"F"},{"firstName":"Chandler","lastName":"Hammes","tz":"101353308","mi":"332852894","clearance":"0","rnk":"unknown","nstype":"G","rld":"2027-01-08 00:00:00.0","hr":"ads2","birthday":"1984-12-10 00:00:00.0","sex":"M"},{"firstName":"Oswald","lastName":"Auer","tz":"176189314","mi":"725019863","clearance":"10","rnk":"rookie","nstype":"F","rld":"2021-10-30 00:00:00.0","hr":"ads3","birthday":"2010-03-27 00:00:00.0","sex":"M"},{"firstName":"Jarret","lastName":"Rosenbaum","tz":"179871678","mi":"354416552","clearance":"0","rnk":"ultimate","nstype":"C","rld":"2021-09-11 00:00:00.0","hr":"ads2","birthday":"2017-12-13 00:00:00.0","sex":"F"},{"firstName":"Andrew","lastName":"Lubowitz","tz":"928066182","mi":"256097474","clearance":"8","rnk":"champion","nstype":"E","rld":"2015-10-22 00:00:00.0","hr":"ads6","birthday":"1993-07-08 00:00:00.0","sex":"M"},{"firstName":"Trevor","lastName":"Jerde","tz":"206079758","mi":"73910813","clearance":"6","rnk":"ultimate","nstype":"E","rld":"2023-07-14 00:00:00.0","hr":"ads5","birthday":"2017-04-02 00:00:00.0","sex":"M"},{"firstName":"Shakira","lastName":"Lemke","tz":"989529052","mi":"772527127","clearance":"8","rnk":"champion","nstype":"B","rld":"2021-07-22 00:00:00.0","hr":"ads5","birthday":"2009-02-07 00:00:00.0","sex":"M"},{"firstName":"Lucy","lastName":"Runolfsdottir","tz":"984924456","mi":"222002093","clearance":"4","rnk":"rookie","nstype":"E","rld":"2019-02-02 00:00:00.0","hr":"ads3","birthday":"1997-03-01 00:00:00.0","sex":"F"},{"firstName":"Emilio","lastName":"Cremin","tz":"484921184","mi":"408866122","clearance":"4","rnk":"mega","nstype":"A","rld":"2025-08-22 00:00:00.0","hr":"ads3","birthday":"1993-12-31 00:00:00.0","sex":"M"},{"firstName":"Ila","lastName":"Bernier","tz":"118739051","mi":"398001245","clearance":"0","rnk":"champion","nstype":"B","rld":"2021-03-11 00:00:00.0","hr":"ads6","birthday":"2017-07-12 00:00:00.0","sex":"F"},{"firstName":"Lester","lastName":"Terry","tz":"753269521","mi":"339148624","clearance":"5","rnk":"ultimate","nstype":"D","rld":"2017-05-23 00:00:00.0","hr":"ads4","birthday":"2000-04-29 00:00:00.0","sex":"F"},{"firstName":"Arvilla","lastName":"Pollich","tz":"389340969","mi":"582949059","clearance":"4","rnk":"mega","nstype":"F","rld":"2025-05-12 00:00:00.0","hr":"ads2","birthday":"2012-05-12 00:00:00.0","sex":"M"},{"firstName":"Stacy","lastName":"Wunsch","tz":"458328788","mi":"421482591","clearance":"5","rnk":"unknown","nstype":"A","rld":"2022-11-26 00:00:00.0","hr":"ads1","birthday":"2015-01-22 00:00:00.0","sex":"F"},{"firstName":"Izaiah","lastName":"Huels","tz":"155573199","mi":"194072815","clearance":"5","rnk":"rookie","nstype":"C","rld":"2018-12-05 00:00:00.0","hr":"ads5","birthday":"2012-11-23 00:00:00.0","sex":"M"},{"firstName":"Wyman","lastName":"Grady","tz":"361793318","mi":"707610321","clearance":"2","rnk":"unknown","nstype":"F","rld":"2022-12-07 00:00:00.0","hr":"ads2","birthday":"2004-11-18 00:00:00.0","sex":"F"},{"firstName":"Benton","lastName":"Mitchell","tz":"284930765","mi":"618227877","clearance":"5","rnk":"ultimate","nstype":"F","rld":"2021-03-27 00:00:00.0","hr":"ads2","birthday":"2016-02-19 00:00:00.0","sex":"F"},{"firstName":"Aracely","lastName":"Klein","tz":"420755878","mi":"664928598","clearance":"8","rnk":"mega","nstype":"E","rld":"2021-06-04 00:00:00.0","hr":"ads5","birthday":"2011-01-22 00:00:00.0","sex":"M"},{"firstName":"Keira","lastName":"Davis","tz":"305446999","mi":"948262140","clearance":"0","rnk":"ultimate","nstype":"F","rld":"2019-05-06 00:00:00.0","hr":"ads3","birthday":"1990-05-11 00:00:00.0","sex":"F"},{"firstName":"Chloe","lastName":"Lehner","tz":"527922058","mi":"208777825","clearance":"0","rnk":"mega","nstype":"A","rld":"2024-09-12 00:00:00.0","hr":"ads3","birthday":"2010-10-12 00:00:00.0","sex":"M"},{"firstName":"Augustine","lastName":"Prohaska","tz":"546943515","mi":"220105397","clearance":"10","rnk":"rookie","nstype":"G","rld":"2029-06-06 00:00:00.0","hr":"ads1","birthday":"2007-12-16 00:00:00.0","sex":"F"},{"firstName":"Aiyana","lastName":"Runolfsson","tz":"367811064","mi":"678872360","clearance":"6","rnk":"mega","nstype":"C","rld":"2019-08-09 00:00:00.0","hr":"ads4","birthday":"2002-01-15 00:00:00.0","sex":"M"},{"firstName":"Adelle","lastName":"Abshire","tz":"744515412","mi":"977801049","clearance":"8","rnk":"champion","nstype":"A","rld":"2019-01-11 00:00:00.0","hr":"ads4","birthday":"2015-07-06 00:00:00.0","sex":"M"},{"firstName":"Antonietta","lastName":"Fadel","tz":"878722255","mi":"873182017","clearance":"4","rnk":"ultimate","nstype":"D","rld":"2028-02-23 00:00:00.0","hr":"ads1","birthday":"2003-07-12 00:00:00.0","sex":"M"},{"firstName":"Curtis","lastName":"Kshlerin","tz":"445110661","mi":"190261098","clearance":"9","rnk":"unknown","nstype":"D","rld":"2026-09-20 00:00:00.0","hr":"ads3","birthday":"2007-05-12 00:00:00.0","sex":"F"},{"firstName":"Lucy","lastName":"Rohan","tz":"543874135","mi":"934118462","clearance":"2","rnk":"rookie","nstype":"G","rld":"2015-08-22 00:00:00.0","hr":"ads5","birthday":"2004-05-22 00:00:00.0","sex":"M"},{"firstName":"Blaze","lastName":"Skiles","tz":"935967596","mi":"637490178","clearance":"6","rnk":"unknown","nstype":"G","rld":"2018-12-04 00:00:00.0","hr":"ads1","birthday":"2018-02-08 00:00:00.0","sex":"F"},{"firstName":"Aryanna","lastName":"O'Reilly","tz":"740509765","mi":"704882903","clearance":"0","rnk":"ultimate","nstype":"A","rld":"2020-07-08 00:00:00.0","hr":"ads3","birthday":"2009-01-02 00:00:00.0","sex":"F"},{"firstName":"Fabiola","lastName":"Ebert","tz":"254588270","mi":"952507416","clearance":"10","rnk":"mega","nstype":"F","rld":"2022-04-06 00:00:00.0","hr":"ads6","birthday":"2019-05-28 00:00:00.0","sex":"M"},{"firstName":"Celia","lastName":"Keeling","tz":"873737068","mi":"474266144","clearance":"5","rnk":"unknown","nstype":"F","rld":"2022-02-20 00:00:00.0","hr":"ads2","birthday":"2018-05-15 00:00:00.0","sex":"F"},{"firstName":"Jeffery","lastName":"Anderson","tz":"552864266","mi":"926548086","clearance":"10","rnk":"ultimate","nstype":"H","rld":"2026-04-30 00:00:00.0","hr":"ads1","birthday":"2011-05-07 00:00:00.0","sex":"F"},{"firstName":"Jarvis","lastName":"Cremin","tz":"300585775","mi":"835417147","clearance":"0","rnk":"rookie","nstype":"C","rld":"2021-10-17 00:00:00.0","hr":"ads4","birthday":"2001-03-12 00:00:00.0","sex":"M"},{"firstName":"Rashawn","lastName":"Hilpert","tz":"640793402","mi":"532893817","clearance":"6","rnk":"unknown","nstype":"G","rld":"2021-03-16 00:00:00.0","hr":"ads5","birthday":"2017-08-02 00:00:00.0","sex":"F"},{"firstName":"Trudie","lastName":"West","tz":"806523890","mi":"989554367","clearance":"6","rnk":"unknown","nstype":"H","rld":"2014-10-03 00:00:00.0","hr":"ads6","birthday":"2010-11-18 00:00:00.0","sex":"F"},{"firstName":"Gene","lastName":"Schuster","tz":"478955792","mi":"101934471","clearance":"3","rnk":"mega","nstype":"F","rld":"2018-06-19 00:00:00.0","hr":"ads5","birthday":"1999-11-16 00:00:00.0","sex":"M"},{"firstName":"Laurence","lastName":"Douglas","tz":"159324037","mi":"466865372","clearance":"5","rnk":"mega","nstype":"G","rld":"2017-12-10 00:00:00.0","hr":"ads4","birthday":"2007-08-15 00:00:00.0","sex":"F"},{"firstName":"Mallory","lastName":"Jakubowski","tz":"546491762","mi":"479798835","clearance":"1","rnk":"rookie","nstype":"F","rld":"2022-02-14 00:00:00.0","hr":"ads6","birthday":"2007-10-07 00:00:00.0","sex":"F"},{"firstName":"Joannie","lastName":"Berge","tz":"937175347","mi":"364497560","clearance":"6","rnk":"ultimate","nstype":"H","rld":"2019-04-26 00:00:00.0","hr":"ads6","birthday":"2004-06-04 00:00:00.0","sex":"M"},{"firstName":"Angelo","lastName":"Eichmann","tz":"455091645","mi":"412878192","clearance":"10","rnk":"mega","nstype":"C","rld":"2029-01-13 00:00:00.0","hr":"ads5","birthday":"2009-02-01 00:00:00.0","sex":"F"},{"firstName":"Jesse","lastName":"Oberbrunner","tz":"670491091","mi":"789434233","clearance":"0","rnk":"ultimate","nstype":"H","rld":"2020-12-15 00:00:00.0","hr":"ads4","birthday":"2000-04-24 00:00:00.0","sex":"F"},{"firstName":"Granville","lastName":"Ullrich","tz":"659880025","mi":"913186623","clearance":"8","rnk":"mega","nstype":"G","rld":"2021-09-17 00:00:00.0","hr":"ads3","birthday":"1998-03-04 00:00:00.0","sex":"F"},{"firstName":"Halie","lastName":"Lockman","tz":"440969582","mi":"397181532","clearance":"3","rnk":"unknown","nstype":"G","rld":"2016-05-04 00:00:00.0","hr":"ads5","birthday":"1990-09-01 00:00:00.0","sex":"F"},{"firstName":"Adela","lastName":"Hickle","tz":"682269600","mi":"539797828","clearance":"3","rnk":"mega","nstype":"C","rld":"2017-08-20 00:00:00.0","hr":"ads6","birthday":"2002-01-15 00:00:00.0","sex":"F"},{"firstName":"Korey","lastName":"Green","tz":"854821568","mi":"374669603","clearance":"2","rnk":"unknown","nstype":"G","rld":"2014-09-20 00:00:00.0","hr":"ads1","birthday":"2005-12-13 00:00:00.0","sex":"M"},{"firstName":"Nikko","lastName":"Sipes","tz":"666270707","mi":"219744519","clearance":"4","rnk":"rookie","nstype":"C","rld":"2019-11-28 00:00:00.0","hr":"ads3","birthday":"2003-02-18 00:00:00.0","sex":"M"},{"firstName":"Norberto","lastName":"Cronin","tz":"380804195","mi":"647787990","clearance":"6","rnk":"ultimate","nstype":"F","rld":"2026-09-19 00:00:00.0","hr":"ads5","birthday":"1998-08-07 00:00:00.0","sex":"M"},{"firstName":"Edmond","lastName":"Kihn","tz":"233338318","mi":"650088747","clearance":"1","rnk":"rookie","nstype":"D","rld":"2020-05-30 00:00:00.0","hr":"ads1","birthday":"2002-03-02 00:00:00.0","sex":"M"},{"firstName":"Kayley","lastName":"Block","tz":"419060926","mi":"489457902","clearance":"3","rnk":"champion","nstype":"B","rld":"2023-07-27 00:00:00.0","hr":"ads4","birthday":"1998-05-30 00:00:00.0","sex":"M"},{"firstName":"Waylon","lastName":"Watsica","tz":"757676150","mi":"311271352","clearance":"1","rnk":"ultimate","nstype":"D","rld":"2020-07-08 00:00:00.0","hr":"ads5","birthday":"2000-06-03 00:00:00.0","sex":"F"},{"firstName":"Jennings","lastName":"Kuhlman","tz":"606408987","mi":"852609007","clearance":"6","rnk":"champion","nstype":"D","rld":"2027-07-11 00:00:00.0","hr":"ads1","birthday":"2004-11-01 00:00:00.0","sex":"M"},{"firstName":"Shirley","lastName":"Hammes","tz":"624562591","mi":"91461896","clearance":"1","rnk":"mega","nstype":"D","rld":"2020-02-19 00:00:00.0","hr":"ads2","birthday":"2017-11-02 00:00:00.0","sex":"M"},{"firstName":"Garrett","lastName":"Nader","tz":"913689238","mi":"573349230","clearance":"7","rnk":"unknown","nstype":"C","rld":"2029-09-15 00:00:00.0","hr":"ads5","birthday":"2011-07-16 00:00:00.0","sex":"M"},{"firstName":"Santiago","lastName":"Beer","tz":"485676241","mi":"195577302","clearance":"1","rnk":"mega","nstype":"A","rld":"2014-07-21 00:00:00.0","hr":"ads3","birthday":"2004-04-05 00:00:00.0","sex":"F"},{"firstName":"Alena","lastName":"Strosin","tz":"218872307","mi":"142904179","clearance":"7","rnk":"unknown","nstype":"B","rld":"2024-02-09 00:00:00.0","hr":"ads4","birthday":"2014-08-17 00:00:00.0","sex":"F"},{"firstName":"Flavio","lastName":"Hettinger","tz":"923560601","mi":"104085987","clearance":"5","rnk":"ultimate","nstype":"G","rld":"2015-04-08 00:00:00.0","hr":"ads2","birthday":"1998-06-22 00:00:00.0","sex":"M"},{"firstName":"Jennyfer","lastName":"Reichel","tz":"685869281","mi":"518383407","clearance":"1","rnk":"unknown","nstype":"C","rld":"2023-02-11 00:00:00.0","hr":"ads6","birthday":"2007-01-18 00:00:00.0","sex":"M"},{"firstName":"Tristian","lastName":"Botsford","tz":"553045295","mi":"793843001","clearance":"9","rnk":"rookie","nstype":"E","rld":"2017-12-09 00:00:00.0","hr":"ads1","birthday":"1995-10-29 00:00:00.0","sex":"M"},{"firstName":"Effie","lastName":"Olson","tz":"125186809","mi":"938055645","clearance":"1","rnk":"rookie","nstype":"E","rld":"2014-07-04 00:00:00.0","hr":"ads3","birthday":"2016-01-06 00:00:00.0","sex":"F"},{"firstName":"Valentin","lastName":"Ebert","tz":"673178083","mi":"937355472","clearance":"3","rnk":"ultimate","nstype":"A","rld":"2023-07-09 00:00:00.0","hr":"ads2","birthday":"2008-10-17 00:00:00.0","sex":"F"},{"firstName":"Rico","lastName":"Murray","tz":"689506525","mi":"397298045","clearance":"5","rnk":"champion","nstype":"D","rld":"2022-01-14 00:00:00.0","hr":"ads2","birthday":"2018-07-18 00:00:00.0","sex":"M"},{"firstName":"Maci","lastName":"Larkin","tz":"156336091","mi":"849722867","clearance":"3","rnk":"ultimate","nstype":"G","rld":"2027-08-26 00:00:00.0","hr":"ads2","birthday":"2011-05-18 00:00:00.0","sex":"M"},{"firstName":"Sylvia","lastName":"Witting","tz":"943290890","mi":"539774271","clearance":"2","rnk":"mega","nstype":"D","rld":"2020-02-25 00:00:00.0","hr":"ads5","birthday":"2013-05-24 00:00:00.0","sex":"F"},{"firstName":"Antone","lastName":"Murphy","tz":"221950728","mi":"85809897","clearance":"2","rnk":"ultimate","nstype":"F","rld":"2020-07-13 00:00:00.0","hr":"ads4","birthday":"2015-02-10 00:00:00.0","sex":"F"},{"firstName":"Mathew","lastName":"Pfeffer","tz":"723930558","mi":"602942630","clearance":"5","rnk":"unknown","nstype":"A","rld":"2022-12-19 00:00:00.0","hr":"ads6","birthday":"1990-10-19 00:00:00.0","sex":"M"},{"firstName":"Mia","lastName":"Farrell","tz":"167333178","mi":"370492293","clearance":"8","rnk":"champion","nstype":"H","rld":"2020-07-09 00:00:00.0","hr":"ads2","birthday":"2008-11-15 00:00:00.0","sex":"M"},{"firstName":"Pete","lastName":"Murray","tz":"945885663","mi":"838939801","clearance":"2","rnk":"champion","nstype":"C","rld":"2018-10-19 00:00:00.0","hr":"ads6","birthday":"2017-03-09 00:00:00.0","sex":"M"},{"firstName":"Wava","lastName":"Von","tz":"236060141","mi":"325516183","clearance":"10","rnk":"ultimate","nstype":"A","rld":"2021-09-06 00:00:00.0","hr":"ads1","birthday":"2007-09-28 00:00:00.0","sex":"F"},{"firstName":"Missouri","lastName":"Beatty","tz":"560951584","mi":"482200638","clearance":"6","rnk":"unknown","nstype":"H","rld":"2015-08-17 00:00:00.0","hr":"ads5","birthday":"2005-11-10 00:00:00.0","sex":"F"},{"firstName":"Zack","lastName":"Brown","tz":"173226309","mi":"913132190","clearance":"3","rnk":"mega","nstype":"D","rld":"2018-11-06 00:00:00.0","hr":"ads3","birthday":"2011-08-30 00:00:00.0","sex":"F"},{"firstName":"Avery","lastName":"Runolfsson","tz":"376294864","mi":"698456664","clearance":"8","rnk":"ultimate","nstype":"H","rld":"2022-08-12 00:00:00.0","hr":"ads6","birthday":"1989-06-07 00:00:00.0","sex":"F"},{"firstName":"Alexzander","lastName":"Mann","tz":"430254961","mi":"951576433","clearance":"5","rnk":"unknown","nstype":"E","rld":"2019-12-19 00:00:00.0","hr":"ads5","birthday":"1992-08-15 00:00:00.0","sex":"F"},{"firstName":"Amy","lastName":"Boehm","tz":"827159823","mi":"799219297","clearance":"8","rnk":"rookie","nstype":"B","rld":"2025-05-08 00:00:00.0","hr":"ads6","birthday":"2011-11-14 00:00:00.0","sex":"M"},{"firstName":"Chaya","lastName":"Hirthe","tz":"538274721","mi":"912129886","clearance":"1","rnk":"rookie","nstype":"G","rld":"2019-05-04 00:00:00.0","hr":"ads2","birthday":"2012-12-16 00:00:00.0","sex":"F"},{"firstName":"Judy","lastName":"McDermott","tz":"377302419","mi":"342740855","clearance":"10","rnk":"mega","nstype":"C","rld":"2017-01-08 00:00:00.0","hr":"ads5","birthday":"2008-10-17 00:00:00.0","sex":"M"},{"firstName":"Ramiro","lastName":"Weimann","tz":"420737520","mi":"70189478","clearance":"5","rnk":"unknown","nstype":"A","rld":"2023-06-01 00:00:00.0","hr":"ads4","birthday":"2010-12-21 00:00:00.0","sex":"F"},{"firstName":"Kim","lastName":"Schinner","tz":"380967661","mi":"879240273","clearance":"3","rnk":"ultimate","nstype":"B","rld":"2023-06-29 00:00:00.0","hr":"ads6","birthday":"2015-01-01 00:00:00.0","sex":"M"},{"firstName":"Lisa","lastName":"Hayes","tz":"706587367","mi":"841477899","clearance":"10","rnk":"unknown","nstype":"H","rld":"2026-10-08 00:00:00.0","hr":"ads4","birthday":"2011-04-25 00:00:00.0","sex":"F"},{"firstName":"Stanford","lastName":"Haag","tz":"975798067","mi":"277478961","clearance":"6","rnk":"champion","nstype":"G","rld":"2028-12-30 00:00:00.0","hr":"ads2","birthday":"1984-12-17 00:00:00.0","sex":"F"},{"firstName":"Alvis","lastName":"Kautzer","tz":"470134396","mi":"553269056","clearance":"3","rnk":"ultimate","nstype":"F","rld":"2021-09-15 00:00:00.0","hr":"ads1","birthday":"1998-12-30 00:00:00.0","sex":"M"},{"firstName":"Curt","lastName":"Hagenes","tz":"932058209","mi":"44457814","clearance":"3","rnk":"unknown","nstype":"B","rld":"2021-01-13 00:00:00.0","hr":"ads5","birthday":"2020-01-05 00:00:00.0","sex":"F"},{"firstName":"Lilyan","lastName":"Rice","tz":"461468019","mi":"848327741","clearance":"6","rnk":"rookie","nstype":"D","rld":"2020-11-13 00:00:00.0","hr":"ads5","birthday":"2005-03-10 00:00:00.0","sex":"F"},{"firstName":"Loyal","lastName":"Wilderman","tz":"790212617","mi":"20310134","clearance":"4","rnk":"ultimate","nstype":"C","rld":"2020-01-27 00:00:00.0","hr":"ads3","birthday":"2016-12-19 00:00:00.0","sex":"F"},{"firstName":"Jaime","lastName":"Shanahan","tz":"384525929","mi":"765590783","clearance":"0","rnk":"mega","nstype":"B","rld":"2012-04-02 00:00:00.0","hr":"ads5","birthday":"2019-08-18 00:00:00.0","sex":"F"},{"firstName":"Christopher","lastName":"Jaskolski","tz":"908318447","mi":"576360388","clearance":"10","rnk":"unknown","nstype":"D","rld":"2017-10-28 00:00:00.0","hr":"ads5","birthday":"2001-02-25 00:00:00.0","sex":"M"},{"firstName":"Sylvia","lastName":"Price","tz":"234489094","mi":"218560423","clearance":"0","rnk":"unknown","nstype":"G","rld":"2024-01-28 00:00:00.0","hr":"ads5","birthday":"1992-07-15 00:00:00.0","sex":"F"},{"firstName":"Alec","lastName":"Dooley","tz":"781832597","mi":"754195713","clearance":"6","rnk":"mega","nstype":"A","rld":"2021-11-12 00:00:00.0","hr":"ads4","birthday":"2008-10-06 00:00:00.0","sex":"F"},{"firstName":"Peyton","lastName":"Kreiger","tz":"689538460","mi":"791266271","clearance":"3","rnk":"unknown","nstype":"D","rld":"2011-03-29 00:00:00.0","hr":"ads3","birthday":"2015-09-19 00:00:00.0","sex":"M"},{"firstName":"Blanca","lastName":"Mohr","tz":"897556759","mi":"520300126","clearance":"9","rnk":"ultimate","nstype":"A","rld":"2022-09-03 00:00:00.0","hr":"ads4","birthday":"2004-05-18 00:00:00.0","sex":"F"},{"firstName":"Selina","lastName":"Brakus","tz":"954712154","mi":"100658583","clearance":"0","rnk":"mega","nstype":"D","rld":"2017-03-28 00:00:00.0","hr":"ads3","birthday":"2001-08-26 00:00:00.0","sex":"F"},{"firstName":"Theron","lastName":"Olson","tz":"943387415","mi":"608241535","clearance":"3","rnk":"unknown","nstype":"G","rld":"2021-08-31 00:00:00.0","hr":"ads2","birthday":"2018-01-26 00:00:00.0","sex":"F"},{"firstName":"Alexanne","lastName":"Stoltenberg","tz":"158737635","mi":"639373242","clearance":"0","rnk":"champion","nstype":"D","rld":"2018-04-03 00:00:00.0","hr":"ads2","birthday":"2018-11-08 00:00:00.0","sex":"M"},{"firstName":"Georgette","lastName":"Feil","tz":"679921221","mi":"6005219","clearance":"5","rnk":"unknown","nstype":"H","rld":"2016-12-02 00:00:00.0","hr":"ads6","birthday":"2006-10-26 00:00:00.0","sex":"F"},{"firstName":"Aric","lastName":"Jerde","tz":"996646717","mi":"478311891","clearance":"9","rnk":"unknown","nstype":"G","rld":"2025-08-21 00:00:00.0","hr":"ads2","birthday":"2013-07-10 00:00:00.0","sex":"M"},{"firstName":"Jake","lastName":"O'Kon","tz":"579206368","mi":"432696554","clearance":"1","rnk":"rookie","nstype":"G","rld":"2020-01-22 00:00:00.0","hr":"ads3","birthday":"1994-08-26 00:00:00.0","sex":"F"},{"firstName":"Margaretta","lastName":"Towne","tz":"875003170","mi":"294144493","clearance":"0","rnk":"rookie","nstype":"E","rld":"2017-05-15 00:00:00.0","hr":"ads1","birthday":"2017-05-22 00:00:00.0","sex":"M"},{"firstName":"Vena","lastName":"Walsh","tz":"462687922","mi":"965335018","clearance":"2","rnk":"champion","nstype":"B","rld":"2019-05-29 00:00:00.0","hr":"ads6","birthday":"2018-11-18 00:00:00.0","sex":"F"},{"firstName":"Magdalen","lastName":"Kshlerin","tz":"358236230","mi":"839131208","clearance":"7","rnk":"mega","nstype":"B","rld":"2021-10-31 00:00:00.0","hr":"ads4","birthday":"1992-12-26 00:00:00.0","sex":"M"},{"firstName":"Zora","lastName":"Herman","tz":"958932600","mi":"292936860","clearance":"4","rnk":"mega","nstype":"B","rld":"2020-12-26 00:00:00.0","hr":"ads2","birthday":"2001-07-30 00:00:00.0","sex":"M"},{"firstName":"Lacy","lastName":"Miller","tz":"960260545","mi":"679652347","clearance":"2","rnk":"champion","nstype":"D","rld":"2018-03-01 00:00:00.0","hr":"ads2","birthday":"2016-02-11 00:00:00.0","sex":"M"},{"firstName":"Guillermo","lastName":"Ferry","tz":"600581235","mi":"742148780","clearance":"2","rnk":"unknown","nstype":"C","rld":"2026-07-02 00:00:00.0","hr":"ads4","birthday":"2005-09-29 00:00:00.0","sex":"F"},{"firstName":"Durward","lastName":"Towne","tz":"767957657","mi":"974622500","clearance":"4","rnk":"ultimate","nstype":"H","rld":"2028-10-06 00:00:00.0","hr":"ads3","birthday":"2007-01-01 00:00:00.0","sex":"M"},{"firstName":"Lynn","lastName":"Becker","tz":"973906001","mi":"63092207","clearance":"10","rnk":"rookie","nstype":"H","rld":"2027-01-07 00:00:00.0","hr":"ads3","birthday":"2007-02-01 00:00:00.0","sex":"M"},{"firstName":"Carol","lastName":"Jerde","tz":"843775420","mi":"898921331","clearance":"10","rnk":"ultimate","nstype":"F","rld":"2015-03-08 00:00:00.0","hr":"ads1","birthday":"2001-03-06 00:00:00.0","sex":"M"},{"firstName":"Whitney","lastName":"Mitchell","tz":"229431853","mi":"290596617","clearance":"1","rnk":"mega","nstype":"F","rld":"2020-06-20 00:00:00.0","hr":"ads3","birthday":"1999-12-10 00:00:00.0","sex":"F"},{"firstName":"Nova","lastName":"Roberts","tz":"905410700","mi":"533800659","clearance":"1","rnk":"mega","nstype":"E","rld":"2021-02-17 00:00:00.0","hr":"ads6","birthday":"1994-11-09 00:00:00.0","sex":"M"},{"firstName":"Shyann","lastName":"Hintz","tz":"438972366","mi":"563442312","clearance":"1","rnk":"champion","nstype":"D","rld":"2022-03-06 00:00:00.0","hr":"ads5","birthday":"2017-12-23 00:00:00.0","sex":"F"},{"firstName":"Sigrid","lastName":"Rohan","tz":"402379614","mi":"720901980","clearance":"9","rnk":"mega","nstype":"F","rld":"2014-07-22 00:00:00.0","hr":"ads4","birthday":"1982-05-13 00:00:00.0","sex":"F"},{"firstName":"Mateo","lastName":"Bechtelar","tz":"802130716","mi":"485333640","clearance":"3","rnk":"unknown","nstype":"G","rld":"2020-11-30 00:00:00.0","hr":"ads5","birthday":"1990-06-27 00:00:00.0","sex":"F"},{"firstName":"Dorthy","lastName":"West","tz":"697412872","mi":"858773139","clearance":"3","rnk":"champion","nstype":"A","rld":"2012-07-09 00:00:00.0","hr":"ads5","birthday":"2011-12-01 00:00:00.0","sex":"F"},{"firstName":"Godfrey","lastName":"Jacobs","tz":"160927604","mi":"191323833","clearance":"6","rnk":"unknown","nstype":"H","rld":"2024-12-05 00:00:00.0","hr":"ads6","birthday":"2016-08-22 00:00:00.0","sex":"F"},{"firstName":"Mariane","lastName":"Bogisich","tz":"717348460","mi":"100418426","clearance":"4","rnk":"champion","nstype":"H","rld":"2020-11-09 00:00:00.0","hr":"ads5","birthday":"2002-07-14 00:00:00.0","sex":"M"},{"firstName":"Marlin","lastName":"Sipes","tz":"418389953","mi":"449930255","clearance":"1","rnk":"mega","nstype":"F","rld":"2023-11-04 00:00:00.0","hr":"ads3","birthday":"2001-10-14 00:00:00.0","sex":"M"},{"firstName":"Florence","lastName":"Kertzmann","tz":"310324298","mi":"763119681","clearance":"10","rnk":"ultimate","nstype":"C","rld":"2022-09-14 00:00:00.0","hr":"ads4","birthday":"1995-03-25 00:00:00.0","sex":"F"},{"firstName":"Toy","lastName":"Schoen","tz":"829496587","mi":"121617266","clearance":"9","rnk":"mega","nstype":"G","rld":"2022-06-01 00:00:00.0","hr":"ads6","birthday":"1993-10-08 00:00:00.0","sex":"F"},{"firstName":"Miracle","lastName":"Hane","tz":"370396822","mi":"715221076","clearance":"8","rnk":"mega","nstype":"A","rld":"2015-04-26 00:00:00.0","hr":"ads4","birthday":"2003-09-20 00:00:00.0","sex":"M"},{"firstName":"Lemuel","lastName":"Powlowski","tz":"434993580","mi":"580485669","clearance":"1","rnk":"mega","nstype":"F","rld":"2025-06-11 00:00:00.0","hr":"ads1","birthday":"2010-11-24 00:00:00.0","sex":"M"},{"firstName":"Jackie","lastName":"Veum","tz":"597353010","mi":"317208958","clearance":"10","rnk":"champion","nstype":"F","rld":"2021-10-02 00:00:00.0","hr":"ads4","birthday":"2000-11-03 00:00:00.0","sex":"M"},{"firstName":"Erin","lastName":"Schinner","tz":"761470814","mi":"37860722","clearance":"5","rnk":"unknown","nstype":"A","rld":"2018-10-29 00:00:00.0","hr":"ads5","birthday":"2007-10-11 00:00:00.0","sex":"F"},{"firstName":"Cathrine","lastName":"Prohaska","tz":"176995793","mi":"498514896","clearance":"1","rnk":"mega","nstype":"F","rld":"2020-01-05 00:00:00.0","hr":"ads3","birthday":"2016-04-14 00:00:00.0","sex":"F"},{"firstName":"Minerva","lastName":"Walker","tz":"417231610","mi":"352105824","clearance":"8","rnk":"ultimate","nstype":"C","rld":"2026-08-25 00:00:00.0","hr":"ads5","birthday":"2013-03-16 00:00:00.0","sex":"M"},{"firstName":"Giovanni","lastName":"Brekke","tz":"422412411","mi":"707494303","clearance":"4","rnk":"mega","nstype":"C","rld":"2026-01-30 00:00:00.0","hr":"ads2","birthday":"2001-09-25 00:00:00.0","sex":"M"},{"firstName":"Rosamond","lastName":"Witting","tz":"172886277","mi":"767774354","clearance":"8","rnk":"unknown","nstype":"A","rld":"2024-11-21 00:00:00.0","hr":"ads1","birthday":"2011-09-06 00:00:00.0","sex":"M"},{"firstName":"Jordane","lastName":"Koelpin","tz":"264519612","mi":"651167033","clearance":"6","rnk":"rookie","nstype":"H","rld":"2024-05-27 00:00:00.0","hr":"ads1","birthday":"2015-02-20 00:00:00.0","sex":"M"},{"firstName":"Raoul","lastName":"Flatley","tz":"736682881","mi":"329738273","clearance":"6","rnk":"champion","nstype":"B","rld":"2020-10-09 00:00:00.0","hr":"ads3","birthday":"1985-09-27 00:00:00.0","sex":"M"},{"firstName":"Carlotta","lastName":"Hoppe","tz":"272702150","mi":"876119988","clearance":"4","rnk":"champion","nstype":"E","rld":"2020-02-26 00:00:00.0","hr":"ads2","birthday":"2005-04-25 00:00:00.0","sex":"F"},{"firstName":"Tiara","lastName":"Turcotte","tz":"711543439","mi":"419775795","clearance":"10","rnk":"champion","nstype":"F","rld":"2018-11-01 00:00:00.0","hr":"ads3","birthday":"2004-01-08 00:00:00.0","sex":"M"},{"firstName":"Alta","lastName":"Ruecker","tz":"740406186","mi":"976537942","clearance":"9","rnk":"unknown","nstype":"H","rld":"2018-06-05 00:00:00.0","hr":"ads3","birthday":"1999-07-29 00:00:00.0","sex":"M"},{"firstName":"Laverna","lastName":"D'Amore","tz":"916164320","mi":"46602240","clearance":"9","rnk":"ultimate","nstype":"D","rld":"2024-03-05 00:00:00.0","hr":"ads1","birthday":"1993-03-06 00:00:00.0","sex":"M"},{"firstName":"Jamie","lastName":"Bosco","tz":"759234180","mi":"821848638","clearance":"4","rnk":"champion","nstype":"E","rld":"2020-02-08 00:00:00.0","hr":"ads1","birthday":"2004-06-04 00:00:00.0","sex":"F"},{"firstName":"Jermaine","lastName":"Pacocha","tz":"727748931","mi":"552168951","clearance":"2","rnk":"ultimate","nstype":"C","rld":"2023-03-05 00:00:00.0","hr":"ads5","birthday":"2020-04-09 00:00:00.0","sex":"M"},{"firstName":"Jackeline","lastName":"Moore","tz":"257114272","mi":"94357000","clearance":"9","rnk":"ultimate","nstype":"C","rld":"2024-04-14 00:00:00.0","hr":"gondor","birthday":"1997-12-28 00:00:00.0","sex":"M"},{"firstName":"Erik","lastName":"Stokes","tz":"247866486","mi":"78175125","clearance":"1","rnk":"ultimate","nstype":"F","rld":"2020-06-24 00:00:00.0","hr":"valhalla","birthday":"2004-08-28 00:00:00.0","sex":"F"},{"firstName":"Stacey","lastName":"Zboncak","tz":"698828654","mi":"813805778","clearance":"1","rnk":"champion","nstype":"G","rld":"2020-02-11 00:00:00.0","hr":"wallmart","birthday":"2004-05-06 00:00:00.0","sex":"M"},{"firstName":"Rachelle","lastName":"Lowe","tz":"679488809","mi":"541048376","clearance":"7","rnk":"unknown","nstype":"B","rld":"2020-12-13 00:00:00.0","hr":"valhalla","birthday":"2018-10-20 00:00:00.0","sex":"F"},{"firstName":"Josefina","lastName":"Kerluke","tz":"927678201","mi":"46751366","clearance":"9","rnk":"mega","nstype":"A","rld":"2020-11-07 00:00:00.0","hr":"wallmart","birthday":"1996-02-17 00:00:00.0","sex":"M"},{"firstName":"Cathrine","lastName":"Carroll","tz":"681141677","mi":"180899253","clearance":"0","rnk":"mega","nstype":"B","rld":"2020-02-14 00:00:00.0","hr":"gondor","birthday":"2002-06-17 00:00:00.0","sex":"M"},{"firstName":"Jordon","lastName":"Jacobson","tz":"137750923","mi":"779924789","clearance":"3","rnk":"rookie","nstype":"E","rld":"2023-12-10 00:00:00.0","hr":"valhalla","birthday":"2007-02-26 00:00:00.0","sex":"M"},{"firstName":"Heloise","lastName":"Swaniawski","tz":"720388081","mi":"242381254","clearance":"5","rnk":"mega","nstype":"B","rld":"2017-11-13 00:00:00.0","hr":"gondor","birthday":"2001-09-02 00:00:00.0","sex":"M"},{"firstName":"Yoshiko","lastName":"Bogisich","tz":"515914505","mi":"414137291","clearance":"2","rnk":"rookie","nstype":"H","rld":"2019-04-17 00:00:00.0","hr":"mordor","birthday":"2012-10-23 00:00:00.0","sex":"F"},{"firstName":"Alaina","lastName":"Williamson","tz":"695867952","mi":"793665871","clearance":"1","rnk":"champion","nstype":"H","rld":"2021-02-09 00:00:00.0","hr":"wallmart","birthday":"2010-07-03 00:00:00.0","sex":"M"},{"firstName":"Oswaldo","lastName":"Auer","tz":"755266251","mi":"809496344","clearance":"1","rnk":"ultimate","nstype":"E","rld":"2018-04-14 00:00:00.0","hr":"mordor","birthday":"1995-10-21 00:00:00.0","sex":"F"},{"firstName":"Clark","lastName":"Feeney","tz":"446777823","mi":"63846520","clearance":"7","rnk":"unknown","nstype":"F","rld":"2018-04-14 00:00:00.0","hr":"mordor","birthday":"2011-05-20 00:00:00.0","sex":"F"},{"firstName":"Celine","lastName":"Mraz","tz":"126673367","mi":"226073209","clearance":"4","rnk":"mega","nstype":"B","rld":"2020-01-29 00:00:00.0","hr":"gondor","birthday":"2014-07-28 00:00:00.0","sex":"M"},{"firstName":"Berry","lastName":"Vandervort","tz":"562998849","mi":"487437390","clearance":"8","rnk":"mega","nstype":"H","rld":"2019-01-08 00:00:00.0","hr":"valhalla","birthday":"2006-04-06 00:00:00.0","sex":"M"},{"firstName":"Oma","lastName":"Lind","tz":"396588873","mi":"499917281","clearance":"3","rnk":"rookie","nstype":"E","rld":"2021-07-12 00:00:00.0","hr":"gondor","birthday":"2002-10-20 00:00:00.0","sex":"F"},{"firstName":"Roderick","lastName":"Gislason","tz":"491939674","mi":"90268904","clearance":"5","rnk":"champion","nstype":"H","rld":"2019-09-26 00:00:00.0","hr":"valhalla","birthday":"2006-10-31 00:00:00.0","sex":"F"},{"firstName":"Kenyatta","lastName":"Kirlin","tz":"531058154","mi":"79397455","clearance":"4","rnk":"mega","nstype":"C","rld":"2023-06-19 00:00:00.0","hr":"wallmart","birthday":"2010-02-04 00:00:00.0","sex":"M"},{"firstName":"Karine","lastName":"Jaskolski","tz":"878054725","mi":"744379574","clearance":"9","rnk":"rookie","nstype":"G","rld":"2022-12-28 00:00:00.0","hr":"gondor","birthday":"2015-12-06 00:00:00.0","sex":"F"},{"firstName":"Andres","lastName":"Wolff","tz":"495660599","mi":"68332192","clearance":"5","rnk":"mega","nstype":"F","rld":"2019-10-31 00:00:00.0","hr":"wallmart","birthday":"2010-08-11 00:00:00.0","sex":"F"},{"firstName":"Adan","lastName":"Treutel","tz":"141458364","mi":"982610332","clearance":"1","rnk":"mega","nstype":"E","rld":"2016-07-05 00:00:00.0","hr":"gondor","birthday":"1991-09-28 00:00:00.0","sex":"M"},{"firstName":"Marcia","lastName":"Gleason","tz":"264085390","mi":"885677613","clearance":"0","rnk":"mega","nstype":"E","rld":"2021-11-06 00:00:00.0","hr":"mordor","birthday":"2014-02-27 00:00:00.0","sex":"M"},{"firstName":"Marc","lastName":"Kirlin","tz":"865276042","mi":"399397786","clearance":"0","rnk":"unknown","nstype":"E","rld":"2013-11-25 00:00:00.0","hr":"gondor","birthday":"2012-11-14 00:00:00.0","sex":"F"},{"firstName":"Adriel","lastName":"Gerlach","tz":"778267252","mi":"329957827","clearance":"5","rnk":"mega","nstype":"F","rld":"2016-12-23 00:00:00.0","hr":"gondor","birthday":"2002-03-06 00:00:00.0","sex":"F"},{"firstName":"Sylvia","lastName":"Parisian","tz":"179157607","mi":"448884983","clearance":"5","rnk":"mega","nstype":"H","rld":"2015-01-30 00:00:00.0","hr":"mordor","birthday":"2016-11-22 00:00:00.0","sex":"M"},{"firstName":"Skyla","lastName":"Muller","tz":"302734827","mi":"379785863","clearance":"9","rnk":"ultimate","nstype":"D","rld":"2021-09-19 00:00:00.0","hr":"wallmart","birthday":"2001-07-21 00:00:00.0","sex":"F"},{"firstName":"Gunnar","lastName":"Shields","tz":"192599249","mi":"130585678","clearance":"10","rnk":"mega","nstype":"A","rld":"2020-04-20 00:00:00.0","hr":"wallmart","birthday":"2018-09-27 00:00:00.0","sex":"F"},{"firstName":"Elijah","lastName":"Rutherford","tz":"509902441","mi":"228160685","clearance":"3","rnk":"rookie","nstype":"F","rld":"2020-09-12 00:00:00.0","hr":"valhalla","birthday":"2002-04-18 00:00:00.0","sex":"F"},{"firstName":"Noah","lastName":"Dietrich","tz":"491542700","mi":"988185675","clearance":"1","rnk":"rookie","nstype":"F","rld":"2022-05-04 00:00:00.0","hr":"valhalla","birthday":"2006-12-25 00:00:00.0","sex":"F"},{"firstName":"Brock","lastName":"Bode","tz":"567529979","mi":"830150954","clearance":"0","rnk":"ultimate","nstype":"C","rld":"2024-06-13 00:00:00.0","hr":"mordor","birthday":"1992-01-11 00:00:00.0","sex":"M"},{"firstName":"Reta","lastName":"Mohr","tz":"878997006","mi":"515188639","clearance":"4","rnk":"ultimate","nstype":"B","rld":"2017-05-24 00:00:00.0","hr":"mordor","birthday":"2000-05-24 00:00:00.0","sex":"M"},{"firstName":"Jabari","lastName":"Gleason","tz":"139235030","mi":"548367807","clearance":"8","rnk":"ultimate","nstype":"D","rld":"2021-06-21 00:00:00.0","hr":"gondor","birthday":"2008-02-08 00:00:00.0","sex":"F"},{"firstName":"Sigurd","lastName":"Jenkins","tz":"390227718","mi":"107557235","clearance":"5","rnk":"unknown","nstype":"E","rld":"2028-05-02 00:00:00.0","hr":"mordor","birthday":"1997-07-20 00:00:00.0","sex":"F"},{"firstName":"Adelia","lastName":"McKenzie","tz":"105755656","mi":"916227281","clearance":"3","rnk":"ultimate","nstype":"G","rld":"2024-06-25 00:00:00.0","hr":"valhalla","birthday":"1986-11-03 00:00:00.0","sex":"F"},{"firstName":"Mekhi","lastName":"Feeney","tz":"927099580","mi":"121869572","clearance":"6","rnk":"champion","nstype":"H","rld":"2023-09-05 00:00:00.0","hr":"mordor","birthday":"2006-12-29 00:00:00.0","sex":"M"},{"firstName":"Cory","lastName":"Cruickshank","tz":"807578117","mi":"710001901","clearance":"4","rnk":"mega","nstype":"F","rld":"2023-07-10 00:00:00.0","hr":"mordor","birthday":"2019-06-28 00:00:00.0","sex":"M"},{"firstName":"Jennyfer","lastName":"Streich","tz":"407163948","mi":"420318481","clearance":"8","rnk":"rookie","nstype":"A","rld":"2020-04-15 00:00:00.0","hr":"valhalla","birthday":"2014-10-15 00:00:00.0","sex":"F"},{"firstName":"Mark","lastName":"Schinner","tz":"239791619","mi":"968514806","clearance":"7","rnk":"ultimate","nstype":"F","rld":"2017-02-02 00:00:00.0","hr":"mordor","birthday":"2011-08-14 00:00:00.0","sex":"F"},{"firstName":"Pat","lastName":"Haley","tz":"551099724","mi":"41337506","clearance":"6","rnk":"champion","nstype":"B","rld":"2022-12-14 00:00:00.0","hr":"mordor","birthday":"2009-01-21 00:00:00.0","sex":"F"},{"firstName":"Mateo","lastName":"Streich","tz":"651040974","mi":"191999649","clearance":"8","rnk":"rookie","nstype":"H","rld":"2019-05-01 00:00:00.0","hr":"gondor","birthday":"2005-12-15 00:00:00.0","sex":"F"},{"firstName":"Immanuel","lastName":"Armstrong","tz":"885437731","mi":"613949578","clearance":"7","rnk":"rookie","nstype":"A","rld":"2020-09-06 00:00:00.0","hr":"valhalla","birthday":"2002-11-19 00:00:00.0","sex":"M"},{"firstName":"Aida","lastName":"Crist","tz":"969914621","mi":"663288207","clearance":"3","rnk":"ultimate","nstype":"D","rld":"2025-02-01 00:00:00.0","hr":"gondor","birthday":"2013-01-07 00:00:00.0","sex":"F"},{"firstName":"Kraig","lastName":"Labadie","tz":"860092816","mi":"334511375","clearance":"1","rnk":"mega","nstype":"D","rld":"2021-03-30 00:00:00.0","hr":"mordor","birthday":"2006-07-10 00:00:00.0","sex":"F"},{"firstName":"Collin","lastName":"Fahey","tz":"518225362","mi":"286379596","clearance":"4","rnk":"unknown","nstype":"D","rld":"2023-10-23 00:00:00.0","hr":"gondor","birthday":"1998-10-25 00:00:00.0","sex":"M"},{"firstName":"Cicero","lastName":"Auer","tz":"631444916","mi":"471630453","clearance":"0","rnk":"rookie","nstype":"E","rld":"2014-11-21 00:00:00.0","hr":"wallmart","birthday":"2013-08-30 00:00:00.0","sex":"F"},{"firstName":"Brycen","lastName":"Kerluke","tz":"969702018","mi":"977314656","clearance":"1","rnk":"unknown","nstype":"D","rld":"2019-05-19 00:00:00.0","hr":"mordor","birthday":"2010-07-06 00:00:00.0","sex":"M"},{"firstName":"Dejuan","lastName":"Harvey","tz":"164091316","mi":"378493193","clearance":"8","rnk":"rookie","nstype":"C","rld":"2024-06-27 00:00:00.0","hr":"mordor","birthday":"1998-09-24 00:00:00.0","sex":"M"},{"firstName":"Jonathan","lastName":"Bernhard","tz":"273998187","mi":"838797916","clearance":"3","rnk":"champion","nstype":"A","rld":"2022-07-09 00:00:00.0","hr":"valhalla","birthday":"2002-02-21 00:00:00.0","sex":"M"},{"firstName":"Leola","lastName":"McGlynn","tz":"749576443","mi":"643123074","clearance":"4","rnk":"ultimate","nstype":"E","rld":"2019-02-16 00:00:00.0","hr":"gondor","birthday":"2005-03-07 00:00:00.0","sex":"M"},{"firstName":"Jaime","lastName":"Thiel","tz":"968635532","mi":"560634210","clearance":"2","rnk":"champion","nstype":"C","rld":"2021-10-28 00:00:00.0","hr":"wallmart","birthday":"2017-01-16 00:00:00.0","sex":"M"},{"firstName":"Jayda","lastName":"Connelly","tz":"961893070","mi":"59067063","clearance":"6","rnk":"rookie","nstype":"E","rld":"2019-10-10 00:00:00.0","hr":"mordor","birthday":"2009-10-29 00:00:00.0","sex":"F"},{"firstName":"Rod","lastName":"Wiza","tz":"194524500","mi":"503135046","clearance":"5","rnk":"champion","nstype":"A","rld":"2016-01-28 00:00:00.0","hr":"wallmart","birthday":"2007-09-09 00:00:00.0","sex":"F"},{"firstName":"Reuben","lastName":"Leannon","tz":"454940172","mi":"217232384","clearance":"4","rnk":"ultimate","nstype":"D","rld":"2017-05-01 00:00:00.0","hr":"gondor","birthday":"2012-08-30 00:00:00.0","sex":"F"},{"firstName":"Shaylee","lastName":"Hamill","tz":"645802547","mi":"199503409","clearance":"10","rnk":"champion","nstype":"C","rld":"2021-05-08 00:00:00.0","hr":"mordor","birthday":"1999-04-10 00:00:00.0","sex":"M"},{"firstName":"Hortense","lastName":"Rau","tz":"935986463","mi":"48540464","clearance":"1","rnk":"unknown","nstype":"B","rld":"2020-01-21 00:00:00.0","hr":"mordor","birthday":"2018-05-02 00:00:00.0","sex":"F"},{"firstName":"Elenora","lastName":"Nader","tz":"375910304","mi":"642786249","clearance":"8","rnk":"champion","nstype":"A","rld":"2022-07-19 00:00:00.0","hr":"wallmart","birthday":"2018-04-23 00:00:00.0","sex":"M"},{"firstName":"Reece","lastName":"Shields","tz":"275230803","mi":"122201052","clearance":"2","rnk":"mega","nstype":"E","rld":"2023-07-24 00:00:00.0","hr":"gondor","birthday":"2012-02-03 00:00:00.0","sex":"M"},{"firstName":"Rosalee","lastName":"Hermiston","tz":"307463893","mi":"38806344","clearance":"9","rnk":"ultimate","nstype":"A","rld":"2016-11-19 00:00:00.0","hr":"mordor","birthday":"2004-10-14 00:00:00.0","sex":"M"},{"firstName":"Destiney","lastName":"Quigley","tz":"714739869","mi":"600311057","clearance":"4","rnk":"mega","nstype":"A","rld":"2022-03-01 00:00:00.0","hr":"gondor","birthday":"2012-07-12 00:00:00.0","sex":"M"},{"firstName":"Rudy","lastName":"Reichert","tz":"848724639","mi":"820551095","clearance":"9","rnk":"mega","nstype":"H","rld":"2018-12-08 00:00:00.0","hr":"gondor","birthday":"2006-08-26 00:00:00.0","sex":"M"},{"firstName":"Hugh","lastName":"Considine","tz":"747332062","mi":"67303417","clearance":"6","rnk":"ultimate","nstype":"D","rld":"2019-03-04 00:00:00.0","hr":"gondor","birthday":"2010-05-29 00:00:00.0","sex":"F"},{"firstName":"Isobel","lastName":"Heathcote","tz":"672033974","mi":"2138911","clearance":"1","rnk":"champion","nstype":"A","rld":"2018-05-03 00:00:00.0","hr":"mordor","birthday":"2015-09-18 00:00:00.0","sex":"M"},{"firstName":"Brenden","lastName":"Fritsch","tz":"536723851","mi":"850268454","clearance":"7","rnk":"champion","nstype":"F","rld":"2016-04-23 00:00:00.0","hr":"valhalla","birthday":"2004-01-30 00:00:00.0","sex":"F"},{"firstName":"Aida","lastName":"Hills","tz":"721586238","mi":"638887118","clearance":"10","rnk":"mega","nstype":"C","rld":"2020-05-01 00:00:00.0","hr":"gondor","birthday":"2000-12-10 00:00:00.0","sex":"F"},{"firstName":"Godfrey","lastName":"Wiza","tz":"939885695","mi":"985799039","clearance":"4","rnk":"champion","nstype":"D","rld":"2016-04-25 00:00:00.0","hr":"mordor","birthday":"2004-03-30 00:00:00.0","sex":"F"},{"firstName":"Dalton","lastName":"Ankunding","tz":"685184905","mi":"909893460","clearance":"6","rnk":"ultimate","nstype":"A","rld":"2029-03-02 00:00:00.0","hr":"mordor","birthday":"2012-08-22 00:00:00.0","sex":"M"},{"firstName":"Tate","lastName":"Ferry","tz":"467379640","mi":"808043411","clearance":"0","rnk":"rookie","nstype":"G","rld":"2016-09-28 00:00:00.0","hr":"gondor","birthday":"1993-05-11 00:00:00.0","sex":"F"},{"firstName":"Jordy","lastName":"Simonis","tz":"134989821","mi":"308970467","clearance":"8","rnk":"champion","nstype":"A","rld":"2023-07-14 00:00:00.0","hr":"valhalla","birthday":"2014-04-21 00:00:00.0","sex":"F"},{"firstName":"Kade","lastName":"Goldner","tz":"380210294","mi":"870039612","clearance":"7","rnk":"rookie","nstype":"F","rld":"2026-12-08 00:00:00.0","hr":"gondor","birthday":"1992-04-02 00:00:00.0","sex":"M"},{"firstName":"Reinhold","lastName":"Waelchi","tz":"899470488","mi":"231883197","clearance":"2","rnk":"unknown","nstype":"B","rld":"2020-05-01 00:00:00.0","hr":"gondor","birthday":"2008-07-23 00:00:00.0","sex":"F"},{"firstName":"Selmer","lastName":"Mann","tz":"333608545","mi":"340435744","clearance":"4","rnk":"mega","nstype":"E","rld":"2024-11-27 00:00:00.0","hr":"wallmart","birthday":"2003-10-05 00:00:00.0","sex":"F"},{"firstName":"Gretchen","lastName":"Waters","tz":"344633755","mi":"268952048","clearance":"5","rnk":"unknown","nstype":"H","rld":"2025-12-29 00:00:00.0","hr":"valhalla","birthday":"2011-05-31 00:00:00.0","sex":"F"},{"firstName":"Chadrick","lastName":"Morar","tz":"917465478","mi":"711434168","clearance":"10","rnk":"champion","nstype":"G","rld":"2024-07-07 00:00:00.0","hr":"wallmart","birthday":"2011-12-28 00:00:00.0","sex":"M"},{"firstName":"Berenice","lastName":"Cartwright","tz":"767166325","mi":"703048607","clearance":"6","rnk":"champion","nstype":"F","rld":"2023-07-03 00:00:00.0","hr":"mordor","birthday":"2017-02-14 00:00:00.0","sex":"F"},{"firstName":"Kamryn","lastName":"Schultz","tz":"534469788","mi":"307952579","clearance":"7","rnk":"mega","nstype":"H","rld":"2024-11-03 00:00:00.0","hr":"mordor","birthday":"2005-03-08 00:00:00.0","sex":"M"},{"firstName":"Clemmie","lastName":"Schamberger","tz":"705620102","mi":"938948646","clearance":"8","rnk":"champion","nstype":"G","rld":"2021-08-01 00:00:00.0","hr":"gondor","birthday":"2015-05-02 00:00:00.0","sex":"M"},{"firstName":"Carmelo","lastName":"Legros","tz":"821968252","mi":"941951438","clearance":"1","rnk":"unknown","nstype":"B","rld":"2020-12-11 00:00:00.0","hr":"wallmart","birthday":"2002-02-14 00:00:00.0","sex":"F"},{"firstName":"Anabelle","lastName":"Swift","tz":"485257158","mi":"578971575","clearance":"7","rnk":"rookie","nstype":"B","rld":"2027-10-25 00:00:00.0","hr":"mordor","birthday":"2012-10-29 00:00:00.0","sex":"F"},{"firstName":"Gabriel","lastName":"Paucek","tz":"648589067","mi":"434359946","clearance":"3","rnk":"mega","nstype":"G","rld":"2022-06-12 00:00:00.0","hr":"valhalla","birthday":"2009-12-15 00:00:00.0","sex":"F"},{"firstName":"Elissa","lastName":"Littel","tz":"710102518","mi":"712365017","clearance":"7","rnk":"champion","nstype":"F","rld":"2015-01-24 00:00:00.0","hr":"wallmart","birthday":"2011-07-22 00:00:00.0","sex":"M"},{"firstName":"Lulu","lastName":"Jacobs","tz":"291697811","mi":"830877084","clearance":"6","rnk":"unknown","nstype":"A","rld":"2023-02-04 00:00:00.0","hr":"gondor","birthday":"2003-02-22 00:00:00.0","sex":"M"},{"firstName":"Nigel","lastName":"Stracke","tz":"568721674","mi":"28616256","clearance":"10","rnk":"ultimate","nstype":"H","rld":"2026-03-02 00:00:00.0","hr":"gondor","birthday":"1992-08-31 00:00:00.0","sex":"F"},{"firstName":"Taya","lastName":"McClure","tz":"614210284","mi":"478715069","clearance":"3","rnk":"mega","nstype":"B","rld":"2027-04-13 00:00:00.0","hr":"valhalla","birthday":"1992-04-27 00:00:00.0","sex":"M"},{"firstName":"Jay","lastName":"Harvey","tz":"135327807","mi":"845747550","clearance":"3","rnk":"rookie","nstype":"G","rld":"2024-05-14 00:00:00.0","hr":"wallmart","birthday":"1995-08-02 00:00:00.0","sex":"F"},{"firstName":"Brittany","lastName":"Johnson","tz":"871105565","mi":"607097176","clearance":"4","rnk":"rookie","nstype":"G","rld":"2023-06-15 00:00:00.0","hr":"valhalla","birthday":"2009-12-14 00:00:00.0","sex":"F"},{"firstName":"Geovanni","lastName":"Greenfelder","tz":"409529625","mi":"952051957","clearance":"0","rnk":"mega","nstype":"E","rld":"2025-02-23 00:00:00.0","hr":"mordor","birthday":"2009-08-01 00:00:00.0","sex":"F"},{"firstName":"Petra","lastName":"Sporer","tz":"472806892","mi":"785549886","clearance":"5","rnk":"rookie","nstype":"A","rld":"2022-04-16 00:00:00.0","hr":"wallmart","birthday":"1997-05-08 00:00:00.0","sex":"F"},{"firstName":"Serenity","lastName":"Stehr","tz":"787454503","mi":"508697827","clearance":"3","rnk":"unknown","nstype":"A","rld":"2022-11-21 00:00:00.0","hr":"wallmart","birthday":"2011-04-17 00:00:00.0","sex":"M"},{"firstName":"Rosetta","lastName":"Parker","tz":"115775660","mi":"233928663","clearance":"7","rnk":"ultimate","nstype":"F","rld":"2021-04-01 00:00:00.0","hr":"gondor","birthday":"2017-08-19 00:00:00.0","sex":"M"},{"firstName":"Deron","lastName":"Schimmel","tz":"364715383","mi":"472412849","clearance":"3","rnk":"rookie","nstype":"B","rld":"2022-07-12 00:00:00.0","hr":"valhalla","birthday":"1994-10-31 00:00:00.0","sex":"M"},{"firstName":"Malcolm","lastName":"Zemlak","tz":"920902889","mi":"131610013","clearance":"6","rnk":"rookie","nstype":"E","rld":"2017-06-11 00:00:00.0","hr":"wallmart","birthday":"1997-08-10 00:00:00.0","sex":"M"},{"firstName":"Brooks","lastName":"Boyle","tz":"412862849","mi":"727054882","clearance":"0","rnk":"champion","nstype":"B","rld":"2025-05-06 00:00:00.0","hr":"valhalla","birthday":"1999-07-09 00:00:00.0","sex":"F"},{"firstName":"Leanne","lastName":"Bahringer","tz":"630601904","mi":"51254547","clearance":"10","rnk":"ultimate","nstype":"G","rld":"2019-07-02 00:00:00.0","hr":"gondor","birthday":"2011-04-13 00:00:00.0","sex":"M"},{"firstName":"Jolie","lastName":"Kirlin","tz":"464089721","mi":"760494459","clearance":"7","rnk":"ultimate","nstype":"F","rld":"2027-08-22 00:00:00.0","hr":"gondor","birthday":"2003-11-05 00:00:00.0","sex":"F"},{"firstName":"Alexandria","lastName":"Herman","tz":"246016000","mi":"776493809","clearance":"10","rnk":"mega","nstype":"D","rld":"2026-07-01 00:00:00.0","hr":"mordor","birthday":"2007-12-19 00:00:00.0","sex":"M"},{"firstName":"Elvera","lastName":"Wiegand","tz":"418842308","mi":"657942101","clearance":"10","rnk":"unknown","nstype":"G","rld":"2018-12-10 00:00:00.0","hr":"mordor","birthday":"1994-02-01 00:00:00.0","sex":"F"},{"firstName":"Elyssa","lastName":"Stracke","tz":"767288327","mi":"701731376","clearance":"7","rnk":"champion","nstype":"C","rld":"2020-03-12 00:00:00.0","hr":"mordor","birthday":"2001-02-16 00:00:00.0","sex":"M"},{"firstName":"Hal","lastName":"Dickinson","tz":"748770864","mi":"821215146","clearance":"7","rnk":"mega","nstype":"F","rld":"2025-09-10 00:00:00.0","hr":"gondor","birthday":"2005-11-16 00:00:00.0","sex":"M"},{"firstName":"Amaya","lastName":"Wilderman","tz":"731769543","mi":"729618620","clearance":"7","rnk":"rookie","nstype":"C","rld":"2026-10-07 00:00:00.0","hr":"valhalla","birthday":"2007-04-13 00:00:00.0","sex":"F"},{"firstName":"Haley","lastName":"Leffler","tz":"666910138","mi":"574518042","clearance":"2","rnk":"champion","nstype":"B","rld":"2027-08-27 00:00:00.0","hr":"mordor","birthday":"2016-12-29 00:00:00.0","sex":"F"},{"firstName":"Claude","lastName":"Nienow","tz":"189457823","mi":"864591984","clearance":"3","rnk":"champion","nstype":"G","rld":"2025-03-28 00:00:00.0","hr":"wallmart","birthday":"2018-08-11 00:00:00.0","sex":"M"},{"firstName":"Leanne","lastName":"Keebler","tz":"972742118","mi":"662248182","clearance":"5","rnk":"rookie","nstype":"G","rld":"2027-09-09 00:00:00.0","hr":"wallmart","birthday":"1986-10-18 00:00:00.0","sex":"F"},{"firstName":"Brennon","lastName":"Crona","tz":"893717652","mi":"684958964","clearance":"1","rnk":"mega","nstype":"H","rld":"2021-01-21 00:00:00.0","hr":"es2","birthday":"2005-05-09 00:00:00.0","sex":"F"},{"firstName":"Ayla","lastName":"Reichel","tz":"342811288","mi":"163545755","clearance":"8","rnk":"mega","nstype":"B","rld":"2020-10-19 00:00:00.0","hr":"es1","birthday":"2019-06-15 00:00:00.0","sex":"M"},{"firstName":"Lesley","lastName":"Stokes","tz":"236371993","mi":"903302048","clearance":"1","rnk":"ultimate","nstype":"D","rld":"2026-05-28 00:00:00.0","hr":"es6","birthday":"2003-02-19 00:00:00.0","sex":"M"},{"firstName":"Delta","lastName":"Kshlerin","tz":"583838214","mi":"691867917","clearance":"0","rnk":"ultimate","nstype":"B","rld":"2021-07-13 00:00:00.0","hr":"wallmart","birthday":"1987-06-16 00:00:00.0","sex":"F"},{"firstName":"Ulises","lastName":"Kozey","tz":"410116453","mi":"683430545","clearance":"4","rnk":"champion","nstype":"D","rld":"2020-06-29 00:00:00.0","hr":"gondor","birthday":"2009-09-26 00:00:00.0","sex":"F"},{"firstName":"Melisa","lastName":"Torphy","tz":"409625530","mi":"856269016","clearance":"3","rnk":"ultimate","nstype":"D","rld":"2016-05-09 00:00:00.0","hr":"es1","birthday":"2018-01-13 00:00:00.0","sex":"M"},{"firstName":"Rowan","lastName":"Sauer","tz":"686276676","mi":"396308995","clearance":"0","rnk":"champion","nstype":"B","rld":"2025-07-22 00:00:00.0","hr":"es1","birthday":"2010-02-12 00:00:00.0","sex":"F"},{"firstName":"Gussie","lastName":"Bode","tz":"776901944","mi":"798848252","clearance":"0","rnk":"rookie","nstype":"H","rld":"2024-12-26 00:00:00.0","hr":"wallmart","birthday":"2015-02-27 00:00:00.0","sex":"M"},{"firstName":"Lloyd","lastName":"Jerde","tz":"972496707","mi":"245666561","clearance":"0","rnk":"mega","nstype":"C","rld":"2018-10-13 00:00:00.0","hr":"gondor","birthday":"2007-11-27 00:00:00.0","sex":"M"},{"firstName":"Dena","lastName":"Anderson","tz":"262603350","mi":"605073408","clearance":"2","rnk":"champion","nstype":"B","rld":"2020-03-04 00:00:00.0","hr":"es4","birthday":"2012-05-25 00:00:00.0","sex":"F"},{"firstName":"Malachi","lastName":"Walsh","tz":"178076329","mi":"289354157","clearance":"0","rnk":"rookie","nstype":"A","rld":"2025-04-29 00:00:00.0","hr":"gondor","birthday":"1995-06-20 00:00:00.0","sex":"F"},{"firstName":"Nyasia","lastName":"Daugherty","tz":"845403062","mi":"137499905","clearance":"2","rnk":"unknown","nstype":"C","rld":"2017-10-16 00:00:00.0","hr":"es3","birthday":"2006-09-10 00:00:00.0","sex":"M"},{"firstName":"Kristian","lastName":"Ferry","tz":"211816764","mi":"360102470","clearance":"9","rnk":"champion","nstype":"E","rld":"2021-08-11 00:00:00.0","hr":"es6","birthday":"1992-05-01 00:00:00.0","sex":"F"},{"firstName":"John","lastName":"Daniel","tz":"828901793","mi":"376475162","clearance":"5","rnk":"rookie","nstype":"B","rld":"2029-01-22 00:00:00.0","hr":"mordor","birthday":"1997-01-11 00:00:00.0","sex":"F"},{"firstName":"Noe","lastName":"Lockman","tz":"709932701","mi":"837874270","clearance":"4","rnk":"champion","nstype":"G","rld":"2025-12-22 00:00:00.0","hr":"wallmart","birthday":"2009-04-25 00:00:00.0","sex":"M"},{"firstName":"Chase","lastName":"Hudson","tz":"465714756","mi":"265154054","clearance":"4","rnk":"rookie","nstype":"A","rld":"2020-03-30 00:00:00.0","hr":"wallmart","birthday":"2008-08-13 00:00:00.0","sex":"M"},{"firstName":"Fiona","lastName":"Parker","tz":"181000464","mi":"171278448","clearance":"5","rnk":"mega","nstype":"G","rld":"2016-09-10 00:00:00.0","hr":"es5","birthday":"2005-08-16 00:00:00.0","sex":"F"},{"firstName":"Josiah","lastName":"Oberbrunner","tz":"960491165","mi":"855824870","clearance":"2","rnk":"ultimate","nstype":"A","rld":"2020-06-19 00:00:00.0","hr":"gondor","birthday":"2009-05-08 00:00:00.0","sex":"F"},{"firstName":"Nadia","lastName":"Flatley","tz":"453452088","mi":"214419859","clearance":"10","rnk":"mega","nstype":"G","rld":"2012-04-26 00:00:00.0","hr":"mordor","birthday":"2004-01-30 00:00:00.0","sex":"M"},{"firstName":"Joy","lastName":"Bashirian","tz":"798238259","mi":"117352898","clearance":"2","rnk":"champion","nstype":"E","rld":"2030-09-30 00:00:00.0","hr":"es6","birthday":"2008-06-18 00:00:00.0","sex":"M"},{"firstName":"Madonna","lastName":"Oberbrunner","tz":"426647210","mi":"300969696","clearance":"4","rnk":"ultimate","nstype":"G","rld":"2018-05-16 00:00:00.0","hr":"mordor","birthday":"1995-01-11 00:00:00.0","sex":"F"},{"firstName":"Mervin","lastName":"Ullrich","tz":"438332017","mi":"681657835","clearance":"8","rnk":"ultimate","nstype":"G","rld":"2022-07-16 00:00:00.0","hr":"es5","birthday":"2009-03-13 00:00:00.0","sex":"M"},{"firstName":"Tevin","lastName":"Breitenberg","tz":"126200922","mi":"868394538","clearance":"8","rnk":"ultimate","nstype":"G","rld":"2022-11-19 00:00:00.0","hr":"es6","birthday":"2007-09-12 00:00:00.0","sex":"F"},{"firstName":"Kailyn","lastName":"Kris","tz":"354771180","mi":"233643509","clearance":"9","rnk":"champion","nstype":"H","rld":"2019-01-30 00:00:00.0","hr":"es5","birthday":"2001-08-15 00:00:00.0","sex":"F"},{"firstName":"Walton","lastName":"Anderson","tz":"964506711","mi":"400677323","clearance":"1","rnk":"rookie","nstype":"A","rld":"2029-06-26 00:00:00.0","hr":"mordor","birthday":"2000-12-05 00:00:00.0","sex":"M"},{"firstName":"Emmy","lastName":"Klocko","tz":"187040787","mi":"835044780","clearance":"6","rnk":"rookie","nstype":"E","rld":"2025-08-24 00:00:00.0","hr":"valhalla","birthday":"2017-01-14 00:00:00.0","sex":"M"},{"firstName":"Casimer","lastName":"Farrell","tz":"872522701","mi":"547051186","clearance":"9","rnk":"ultimate","nstype":"F","rld":"2018-08-03 00:00:00.0","hr":"mordor","birthday":"2002-07-17 00:00:00.0","sex":"F"},{"firstName":"Christian","lastName":"Trantow","tz":"727809261","mi":"961120805","clearance":"10","rnk":"mega","nstype":"F","rld":"2020-06-04 00:00:00.0","hr":"wallmart","birthday":"1992-02-25 00:00:00.0","sex":"F"},{"firstName":"Isadore","lastName":"Zemlak","tz":"566298105","mi":"321461679","clearance":"6","rnk":"ultimate","nstype":"A","rld":"2012-11-19 00:00:00.0","hr":"es4","birthday":"2011-12-01 00:00:00.0","sex":"F"},{"firstName":"Ocie","lastName":"Waelchi","tz":"952308674","mi":"623116325","clearance":"2","rnk":"ultimate","nstype":"D","rld":"2021-08-30 00:00:00.0","hr":"mordor","birthday":"2016-06-09 00:00:00.0","sex":"M"},{"firstName":"Aimee","lastName":"Johnson","tz":"558494142","mi":"488391229","clearance":"8","rnk":"rookie","nstype":"B","rld":"2020-10-01 00:00:00.0","hr":"wallmart","birthday":"2008-10-27 00:00:00.0","sex":"M"},{"firstName":"Zack","lastName":"Hackett","tz":"771967957","mi":"288055382","clearance":"1","rnk":"mega","nstype":"H","rld":"2024-05-30 00:00:00.0","hr":"es4","birthday":"1999-03-02 00:00:00.0","sex":"M"},{"firstName":"Aliyah","lastName":"Corkery","tz":"993235878","mi":"708926066","clearance":"2","rnk":"mega","nstype":"D","rld":"2016-02-13 00:00:00.0","hr":"wallmart","birthday":"2015-08-24 00:00:00.0","sex":"M"},{"firstName":"Elena","lastName":"Kuhlman","tz":"459718888","mi":"323749140","clearance":"10","rnk":"unknown","nstype":"B","rld":"2021-09-29 00:00:00.0","hr":"es4","birthday":"2009-01-20 00:00:00.0","sex":"M"},{"firstName":"Citlalli","lastName":"Heller","tz":"771866381","mi":"834889151","clearance":"7","rnk":"rookie","nstype":"C","rld":"2024-03-24 00:00:00.0","hr":"es2","birthday":"1994-01-18 00:00:00.0","sex":"F"},{"firstName":"Joey","lastName":"Miller","tz":"387040538","mi":"109472542","clearance":"9","rnk":"ultimate","nstype":"E","rld":"2021-05-06 00:00:00.0","hr":"es6","birthday":"2006-09-01 00:00:00.0","sex":"F"},{"firstName":"Laron","lastName":"Sporer","tz":"973658438","mi":"445609744","clearance":"0","rnk":"unknown","nstype":"E","rld":"2021-11-24 00:00:00.0","hr":"wallmart","birthday":"2002-01-09 00:00:00.0","sex":"M"},{"firstName":"Shea","lastName":"Langosh","tz":"149570996","mi":"577809875","clearance":"0","rnk":"rookie","nstype":"F","rld":"2020-08-28 00:00:00.0","hr":"valhalla","birthday":"2004-05-21 00:00:00.0","sex":"M"},{"firstName":"Dustin","lastName":"Kemmer","tz":"608356192","mi":"474479887","clearance":"3","rnk":"mega","nstype":"E","rld":"2021-03-24 00:00:00.0","hr":"es6","birthday":"2019-12-07 00:00:00.0","sex":"F"},{"firstName":"Bernadine","lastName":"Nienow","tz":"628223620","mi":"905998458","clearance":"4","rnk":"mega","nstype":"D","rld":"2014-07-02 00:00:00.0","hr":"es2","birthday":"2013-02-13 00:00:00.0","sex":"M"},{"firstName":"Jeffery","lastName":"Wuckert","tz":"491352092","mi":"399492103","clearance":"10","rnk":"rookie","nstype":"A","rld":"2018-04-30 00:00:00.0","hr":"es6","birthday":"2012-05-27 00:00:00.0","sex":"F"},{"firstName":"Monroe","lastName":"Cormier","tz":"779161207","mi":"52906153","clearance":"9","rnk":"rookie","nstype":"H","rld":"2017-11-17 00:00:00.0","hr":"es3","birthday":"2015-03-09 00:00:00.0","sex":"F"},{"firstName":"Baby","lastName":"Corwin","tz":"477681191","mi":"174294838","clearance":"4","rnk":"ultimate","nstype":"G","rld":"2026-06-26 00:00:00.0","hr":"wallmart","birthday":"2016-02-13 00:00:00.0","sex":"F"},{"firstName":"Jasmin","lastName":"Grant","tz":"267229516","mi":"785279254","clearance":"6","rnk":"unknown","nstype":"G","rld":"2020-04-17 00:00:00.0","hr":"gondor","birthday":"2005-03-06 00:00:00.0","sex":"M"},{"firstName":"Ricky","lastName":"Stokes","tz":"446474785","mi":"958772326","clearance":"10","rnk":"mega","nstype":"E","rld":"2022-06-13 00:00:00.0","hr":"wallmart","birthday":"1990-08-22 00:00:00.0","sex":"F"},{"firstName":"Leatha","lastName":"Batz","tz":"430084517","mi":"890990884","clearance":"3","rnk":"unknown","nstype":"E","rld":"2021-05-16 00:00:00.0","hr":"gondor","birthday":"2000-12-17 00:00:00.0","sex":"M"},{"firstName":"Kellie","lastName":"Willms","tz":"453841553","mi":"283171573","clearance":"7","rnk":"unknown","nstype":"C","rld":"2016-09-04 00:00:00.0","hr":"es2","birthday":"2013-09-10 00:00:00.0","sex":"F"},{"firstName":"Jazmyne","lastName":"McLaughlin","tz":"680754868","mi":"234125616","clearance":"10","rnk":"mega","nstype":"F","rld":"2019-12-25 00:00:00.0","hr":"es2","birthday":"2011-08-27 00:00:00.0","sex":"F"},{"firstName":"Kacey","lastName":"Gulgowski","tz":"515204584","mi":"662584771","clearance":"4","rnk":"rookie","nstype":"E","rld":"2019-11-20 00:00:00.0","hr":"gondor","birthday":"2013-08-04 00:00:00.0","sex":"F"},{"firstName":"Reina","lastName":"Swift","tz":"383510161","mi":"494627304","clearance":"1","rnk":"ultimate","nstype":"F","rld":"2021-12-25 00:00:00.0","hr":"mordor","birthday":"1994-03-03 00:00:00.0","sex":"F"},{"firstName":"Coty","lastName":"Beier","tz":"442781563","mi":"636974419","clearance":"8","rnk":"rookie","nstype":"H","rld":"2021-12-25 00:00:00.0","hr":"wallmart","birthday":"2016-05-20 00:00:00.0","sex":"F"},{"firstName":"Dianna","lastName":"Wilkinson","tz":"526703434","mi":"657584162","clearance":"8","rnk":"ultimate","nstype":"C","rld":"2021-10-14 00:00:00.0","hr":"gondor","birthday":"2004-08-30 00:00:00.0","sex":"F"},{"firstName":"Daija","lastName":"Hansen","tz":"748816980","mi":"550829165","clearance":"4","rnk":"champion","nstype":"C","rld":"2016-01-25 00:00:00.0","hr":"mordor","birthday":"2005-04-26 00:00:00.0","sex":"M"},{"firstName":"Porter","lastName":"Oberbrunner","tz":"141894311","mi":"426864680","clearance":"0","rnk":"unknown","nstype":"D","rld":"2020-04-09 00:00:00.0","hr":"valhalla","birthday":"2016-07-08 00:00:00.0","sex":"F"},{"firstName":"Orie","lastName":"McKenzie","tz":"136775145","mi":"38945848","clearance":"8","rnk":"unknown","nstype":"E","rld":"2018-03-12 00:00:00.0","hr":"wallmart","birthday":"2016-06-03 00:00:00.0","sex":"F"},{"firstName":"Elwyn","lastName":"Schaden","tz":"336042411","mi":"880307490","clearance":"6","rnk":"unknown","nstype":"A","rld":"2022-04-27 00:00:00.0","hr":"wallmart","birthday":"1989-02-07 00:00:00.0","sex":"M"},{"firstName":"Chester","lastName":"Von","tz":"290004761","mi":"957953163","clearance":"2","rnk":"ultimate","nstype":"H","rld":"2023-06-28 00:00:00.0","hr":"gondor","birthday":"2013-10-03 00:00:00.0","sex":"F"},{"firstName":"Emmanuel","lastName":"Bernier","tz":"896215886","mi":"333204586","clearance":"7","rnk":"champion","nstype":"B","rld":"2027-11-11 00:00:00.0","hr":"wallmart","birthday":"2000-09-07 00:00:00.0","sex":"F"},{"firstName":"Jedidiah","lastName":"Sauer","tz":"573442555","mi":"296859668","clearance":"0","rnk":"ultimate","nstype":"G","rld":"2022-02-28 00:00:00.0","hr":"valhalla","birthday":"2002-05-17 00:00:00.0","sex":"F"},{"firstName":"Isom","lastName":"Macejkovic","tz":"573669785","mi":"216315166","clearance":"0","rnk":"mega","nstype":"A","rld":"2014-01-21 00:00:00.0","hr":"gondor","birthday":"2004-06-10 00:00:00.0","sex":"M"},{"firstName":"Buford","lastName":"Rath","tz":"878391788","mi":"561723803","clearance":"9","rnk":"rookie","nstype":"D","rld":"2020-04-14 00:00:00.0","hr":"mordor","birthday":"2010-03-21 00:00:00.0","sex":"F"},{"firstName":"Harry","lastName":"Barton","tz":"370384984","mi":"113924882","clearance":"3","rnk":"champion","nstype":"A","rld":"2017-04-02 00:00:00.0","hr":"valhalla","birthday":"2002-11-08 00:00:00.0","sex":"F"},{"firstName":"Asia","lastName":"Bergnaum","tz":"417383171","mi":"548069753","clearance":"1","rnk":"mega","nstype":"H","rld":"2027-03-13 00:00:00.0","hr":"wallmart","birthday":"2009-06-19 00:00:00.0","sex":"F"},{"firstName":"Marlon","lastName":"Kohler","tz":"969160928","mi":"573362714","clearance":"10","rnk":"unknown","nstype":"F","rld":"2026-08-13 00:00:00.0","hr":"wallmart","birthday":"2015-01-30 00:00:00.0","sex":"M"},{"firstName":"Winifred","lastName":"Quitzon","tz":"986150423","mi":"366304551","clearance":"5","rnk":"rookie","nstype":"F","rld":"2021-06-10 00:00:00.0","hr":"mordor","birthday":"2013-04-21 00:00:00.0","sex":"M"},{"firstName":"Lonzo","lastName":"Simonis","tz":"363183468","mi":"290363770","clearance":"9","rnk":"ultimate","nstype":"C","rld":"2027-03-13 00:00:00.0","hr":"valhalla","birthday":"2002-04-25 00:00:00.0","sex":"F"},{"firstName":"Catalina","lastName":"Dooley","tz":"342112208","mi":"856821798","clearance":"7","rnk":"unknown","nstype":"B","rld":"2021-04-30 00:00:00.0","hr":"gondor","birthday":"2003-07-13 00:00:00.0","sex":"F"},{"firstName":"Bria","lastName":"Legros","tz":"270598071","mi":"326673544","clearance":"3","rnk":"champion","nstype":"G","rld":"2022-12-20 00:00:00.0","hr":"wallmart","birthday":"2013-10-11 00:00:00.0","sex":"F"},{"firstName":"Margarita","lastName":"Cummings","tz":"638331272","mi":"587778783","clearance":"7","rnk":"unknown","nstype":"A","rld":"2021-04-18 00:00:00.0","hr":"wallmart","birthday":"2009-04-25 00:00:00.0","sex":"F"},{"firstName":"Jerry","lastName":"Huels","tz":"188200448","mi":"212494685","clearance":"2","rnk":"mega","nstype":"C","rld":"2022-10-15 00:00:00.0","hr":"valhalla","birthday":"2001-08-14 00:00:00.0","sex":"M"},{"firstName":"Bridget","lastName":"Brown","tz":"533197315","mi":"365437497","clearance":"4","rnk":"unknown","nstype":"F","rld":"2023-05-16 00:00:00.0","hr":"wallmart","birthday":"2003-09-26 00:00:00.0","sex":"M"},{"firstName":"Broderick","lastName":"Bruen","tz":"451012637","mi":"871836430","clearance":"8","rnk":"mega","nstype":"C","rld":"2023-09-22 00:00:00.0","hr":"wallmart","birthday":"2007-11-07 00:00:00.0","sex":"F"},{"firstName":"Eli","lastName":"Ziemann","tz":"600245328","mi":"457541113","clearance":"8","rnk":"champion","nstype":"B","rld":"2029-07-18 00:00:00.0","hr":"wallmart","birthday":"2007-04-14 00:00:00.0","sex":"F"},{"firstName":"King","lastName":"Balistreri","tz":"576248637","mi":"863426567","clearance":"7","rnk":"ultimate","nstype":"A","rld":"2020-10-02 00:00:00.0","hr":"valhalla","birthday":"2001-10-22 00:00:00.0","sex":"M"},{"firstName":"Austen","lastName":"Brown","tz":"443450432","mi":"356343101","clearance":"4","rnk":"ultimate","nstype":"H","rld":"2022-12-29 00:00:00.0","hr":"wallmart","birthday":"2001-05-25 00:00:00.0","sex":"M"},{"firstName":"Kallie","lastName":"Ruecker","tz":"242710226","mi":"739094930","clearance":"9","rnk":"mega","nstype":"G","rld":"2016-07-31 00:00:00.0","hr":"gondor","birthday":"1987-05-09 00:00:00.0","sex":"F"},{"firstName":"Rebecca","lastName":"Jacobson","tz":"291490654","mi":"104486016","clearance":"7","rnk":"unknown","nstype":"C","rld":"2021-01-13 00:00:00.0","hr":"valhalla","birthday":"1991-06-09 00:00:00.0","sex":"F"},{"firstName":"Julien","lastName":"Berge","tz":"724168307","mi":"964889611","clearance":"8","rnk":"champion","nstype":"D","rld":"2022-01-28 00:00:00.0","hr":"wallmart","birthday":"2012-05-15 00:00:00.0","sex":"F"},{"firstName":"Claire","lastName":"Bradtke","tz":"696825637","mi":"232641165","clearance":"9","rnk":"champion","nstype":"D","rld":"2020-03-11 00:00:00.0","hr":"gondor","birthday":"1997-01-08 00:00:00.0","sex":"F"},{"firstName":"Lou","lastName":"Feest","tz":"273622373","mi":"15606355","clearance":"7","rnk":"ultimate","nstype":"B","rld":"2024-04-24 00:00:00.0","hr":"mordor","birthday":"1994-07-30 00:00:00.0","sex":"M"},{"firstName":"Zita","lastName":"Green","tz":"388475360","mi":"218830839","clearance":"1","rnk":"ultimate","nstype":"A","rld":"2019-04-10 00:00:00.0","hr":"wallmart","birthday":"1999-10-10 00:00:00.0","sex":"M"},{"firstName":"Marilyne","lastName":"Block","tz":"799083415","mi":"841487423","clearance":"7","rnk":"mega","nstype":"F","rld":"2023-06-24 00:00:00.0","hr":"gondor","birthday":"2008-11-16 00:00:00.0","sex":"M"},{"firstName":"Granville","lastName":"Quigley","tz":"842239030","mi":"615950620","clearance":"6","rnk":"mega","nstype":"A","rld":"2021-02-26 00:00:00.0","hr":"valhalla","birthday":"2015-07-06 00:00:00.0","sex":"F"},{"firstName":"Louisa","lastName":"Ferry","tz":"924193352","mi":"812978494","clearance":"4","rnk":"champion","nstype":"A","rld":"2020-02-29 00:00:00.0","hr":"mordor","birthday":"2012-04-11 00:00:00.0","sex":"F"},{"firstName":"Jovani","lastName":"Gleichner","tz":"328052717","mi":"236842178","clearance":"1","rnk":"champion","nstype":"D","rld":"2019-06-08 00:00:00.0","hr":"gondor","birthday":"2009-07-28 00:00:00.0","sex":"F"},{"firstName":"Tyson","lastName":"Shields","tz":"422720995","mi":"160181314","clearance":"2","rnk":"rookie","nstype":"D","rld":"2018-08-29 00:00:00.0","hr":"gondor","birthday":"2007-08-23 00:00:00.0","sex":"F"},{"firstName":"Sammie","lastName":"Schneider","tz":"464458330","mi":"199601063","clearance":"4","rnk":"mega","nstype":"E","rld":"2021-11-23 00:00:00.0","hr":"wallmart","birthday":"2006-08-04 00:00:00.0","sex":"M"},{"firstName":"Theodore","lastName":"Kessler","tz":"274968247","mi":"990737134","clearance":"2","rnk":"unknown","nstype":"B","rld":"2026-02-05 00:00:00.0","hr":"mordor","birthday":"2003-03-14 00:00:00.0","sex":"M"},{"firstName":"August","lastName":"Gutkowski","tz":"400843231","mi":"20623191","clearance":"5","rnk":"champion","nstype":"H","rld":"2024-01-29 00:00:00.0","hr":"gondor","birthday":"1994-08-07 00:00:00.0","sex":"F"},{"firstName":"Woodrow","lastName":"Kris","tz":"938296670","mi":"707230270","clearance":"1","rnk":"ultimate","nstype":"D","rld":"2020-06-07 00:00:00.0","hr":"gondor","birthday":"1998-05-08 00:00:00.0","sex":"M"},{"firstName":"Bianka","lastName":"Carroll","tz":"503612962","mi":"13798261","clearance":"9","rnk":"rookie","nstype":"E","rld":"2028-07-22 00:00:00.0","hr":"wallmart","birthday":"2008-03-22 00:00:00.0","sex":"F"},{"firstName":"Amani","lastName":"Kshlerin","tz":"308457985","mi":"626654153","clearance":"2","rnk":"mega","nstype":"E","rld":"2021-07-04 00:00:00.0","hr":"mordor","birthday":"1998-03-14 00:00:00.0","sex":"F"},{"firstName":"Sven","lastName":"Nicolas","tz":"575735733","mi":"791909836","clearance":"3","rnk":"mega","nstype":"G","rld":"2021-07-25 00:00:00.0","hr":"wallmart","birthday":"2006-10-13 00:00:00.0","sex":"F"},{"firstName":"Leone","lastName":"Graham","tz":"427779871","mi":"515652801","clearance":"1","rnk":"unknown","nstype":"C","rld":"2028-04-27 00:00:00.0","hr":"wallmart","birthday":"1992-03-22 00:00:00.0","sex":"M"},{"firstName":"Giovanna","lastName":"Kreiger","tz":"914703145","mi":"278241015","clearance":"5","rnk":"ultimate","nstype":"B","rld":"2020-10-17 00:00:00.0","hr":"mordor","birthday":"2003-05-19 00:00:00.0","sex":"F"},{"firstName":"Adolph","lastName":"Marks","tz":"565861002","mi":"73791639","clearance":"1","rnk":"mega","nstype":"D","rld":"2020-02-15 00:00:00.0","hr":"mordor","birthday":"2014-07-13 00:00:00.0","sex":"M"},{"firstName":"Colby","lastName":"Kreiger","tz":"578476194","mi":"220013081","clearance":"10","rnk":"mega","nstype":"H","rld":"2024-01-14 00:00:00.0","hr":"mordor","birthday":"2015-10-30 00:00:00.0","sex":"F"},{"firstName":"Andy","lastName":"Donnelly","tz":"644355802","mi":"957666141","clearance":"10","rnk":"rookie","nstype":"E","rld":"2026-01-27 00:00:00.0","hr":"wallmart","birthday":"2011-09-02 00:00:00.0","sex":"F"},{"firstName":"Dedric","lastName":"Nitzsche","tz":"633400742","mi":"345697995","clearance":"9","rnk":"rookie","nstype":"F","rld":"2018-08-22 00:00:00.0","hr":"mordor","birthday":"1990-08-30 00:00:00.0","sex":"F"},{"firstName":"Moriah","lastName":"Brakus","tz":"692973670","mi":"14303299","clearance":"8","rnk":"champion","nstype":"A","rld":"2021-08-22 00:00:00.0","hr":"gondor","birthday":"2011-10-01 00:00:00.0","sex":"M"},{"firstName":"Earl","lastName":"Weber","tz":"173827304","mi":"285786610","clearance":"7","rnk":"mega","nstype":"D","rld":"2022-02-03 00:00:00.0","hr":"valhalla","birthday":"2016-08-17 00:00:00.0","sex":"F"},{"firstName":"Tobin","lastName":"Turner","tz":"464429489","mi":"718237922","clearance":"4","rnk":"rookie","nstype":"A","rld":"2020-07-09 00:00:00.0","hr":"mordor","birthday":"2001-02-09 00:00:00.0","sex":"M"},{"firstName":"Ken","lastName":"Huels","tz":"269677480","mi":"669584365","clearance":"10","rnk":"champion","nstype":"F","rld":"2020-01-30 00:00:00.0","hr":"mordor","birthday":"2013-04-07 00:00:00.0","sex":"F"},{"firstName":"Pasquale","lastName":"Borer","tz":"521410506","mi":"187392932","clearance":"3","rnk":"champion","nstype":"B","rld":"2020-10-08 00:00:00.0","hr":"valhalla","birthday":"2012-02-26 00:00:00.0","sex":"F"},{"firstName":"Isabelle","lastName":"Bauch","tz":"341996163","mi":"830958192","clearance":"10","rnk":"ultimate","nstype":"B","rld":"2016-07-30 00:00:00.0","hr":"gondor","birthday":"2016-11-17 00:00:00.0","sex":"F"},{"firstName":"Nicholas","lastName":"Monahan","tz":"295626824","mi":"879934185","clearance":"9","rnk":"ultimate","nstype":"C","rld":"2021-02-14 00:00:00.0","hr":"mordor","birthday":"2007-11-09 00:00:00.0","sex":"M"},{"firstName":"Terrence","lastName":"Parker","tz":"722082112","mi":"879251532","clearance":"10","rnk":"mega","nstype":"C","rld":"2021-07-09 00:00:00.0","hr":"wallmart","birthday":"1989-07-16 00:00:00.0","sex":"F"},{"firstName":"Helene","lastName":"Lockman","tz":"676078363","mi":"429415714","clearance":"9","rnk":"mega","nstype":"A","rld":"2027-05-13 00:00:00.0","hr":"gondor","birthday":"1985-06-20 00:00:00.0","sex":"F"},{"firstName":"Hester","lastName":"Glover","tz":"953034634","mi":"257637609","clearance":"2","rnk":"mega","nstype":"E","rld":"2029-10-20 00:00:00.0","hr":"gondor","birthday":"2007-03-18 00:00:00.0","sex":"M"},{"firstName":"Claudia","lastName":"Littel","tz":"117025288","mi":"871188432","clearance":"1","rnk":"champion","nstype":"A","rld":"2024-03-16 00:00:00.0","hr":"wallmart","birthday":"2001-04-20 00:00:00.0","sex":"F"},{"firstName":"Kariane","lastName":"Spinka","tz":"589305234","mi":"449195604","clearance":"7","rnk":"unknown","nstype":"B","rld":"2019-11-17 00:00:00.0","hr":"mordor","birthday":"2013-08-08 00:00:00.0","sex":"F"},{"firstName":"Emil","lastName":"Koelpin","tz":"477663553","mi":"226859299","clearance":"3","rnk":"ultimate","nstype":"H","rld":"2022-04-16 00:00:00.0","hr":"gondor","birthday":"2015-04-13 00:00:00.0","sex":"M"},{"firstName":"Jeramy","lastName":"Kemmer","tz":"167587948","mi":"218493854","clearance":"0","rnk":"champion","nstype":"H","rld":"2021-01-25 00:00:00.0","hr":"valhalla","birthday":"1997-12-03 00:00:00.0","sex":"M"},{"firstName":"Sister","lastName":"Gleason","tz":"462075490","mi":"239517063","clearance":"6","rnk":"mega","nstype":"A","rld":"2021-03-30 00:00:00.0","hr":"mordor","birthday":"2009-10-11 00:00:00.0","sex":"F"},{"firstName":"Aric","lastName":"Crooks","tz":"804332559","mi":"450763004","clearance":"7","rnk":"ultimate","nstype":"A","rld":"2018-04-06 00:00:00.0","hr":"gondor","birthday":"2015-01-10 00:00:00.0","sex":"M"},{"firstName":"Karine","lastName":"Huels","tz":"853591196","mi":"681039500","clearance":"3","rnk":"ultimate","nstype":"B","rld":"2018-11-30 00:00:00.0","hr":"gondor","birthday":"1998-10-09 00:00:00.0","sex":"F"},{"firstName":"Destini","lastName":"Medhurst","tz":"246972673","mi":"188700923","clearance":"6","rnk":"ultimate","nstype":"C","rld":"2019-07-29 00:00:00.0","hr":"mordor","birthday":"2005-11-25 00:00:00.0","sex":"M"},{"firstName":"Breanne","lastName":"Veum","tz":"562358200","mi":"157881743","clearance":"0","rnk":"champion","nstype":"D","rld":"2016-08-24 00:00:00.0","hr":"gondor","birthday":"1996-09-05 00:00:00.0","sex":"M"},{"firstName":"Michaela","lastName":"Greenfelder","tz":"534846951","mi":"869676110","clearance":"6","rnk":"rookie","nstype":"C","rld":"2025-03-29 00:00:00.0","hr":"mordor","birthday":"2004-09-03 00:00:00.0","sex":"M"},{"firstName":"Elna","lastName":"Schamberger","tz":"517677233","mi":"527777432","clearance":"0","rnk":"mega","nstype":"C","rld":"2025-01-04 00:00:00.0","hr":"valhalla","birthday":"2008-02-26 00:00:00.0","sex":"F"},{"firstName":"Leland","lastName":"Dicki","tz":"399643774","mi":"898457249","clearance":"7","rnk":"unknown","nstype":"A","rld":"2015-07-30 00:00:00.0","hr":"gondor","birthday":"2019-09-28 00:00:00.0","sex":"M"},{"firstName":"Jerrod","lastName":"Reynolds","tz":"861150142","mi":"839168985","clearance":"5","rnk":"ultimate","nstype":"B","rld":"2019-06-14 00:00:00.0","hr":"valhalla","birthday":"2015-09-13 00:00:00.0","sex":"F"},{"firstName":"April","lastName":"Dibbert","tz":"505320788","mi":"382739266","clearance":"7","rnk":"unknown","nstype":"B","rld":"2024-11-18 00:00:00.0","hr":"wallmart","birthday":"2002-11-13 00:00:00.0","sex":"F"},{"firstName":"Ted","lastName":"Towne","tz":"903070134","mi":"652887998","clearance":"3","rnk":"champion","nstype":"B","rld":"2024-07-30 00:00:00.0","hr":"mordor","birthday":"2009-09-24 00:00:00.0","sex":"M"},{"firstName":"Caleigh","lastName":"Borer","tz":"820656791","mi":"113300512","clearance":"4","rnk":"ultimate","nstype":"F","rld":"2026-08-12 00:00:00.0","hr":"mordor","birthday":"2020-11-04 00:00:00.0","sex":"M"},{"firstName":"Eliza","lastName":"Graham","tz":"987332590","mi":"360430958","clearance":"9","rnk":"champion","nstype":"B","rld":"2022-01-24 00:00:00.0","hr":"mordor","birthday":"2020-04-01 00:00:00.0","sex":"M"},{"firstName":"Manley","lastName":"Aufderhar","tz":"605459049","mi":"533220337","clearance":"2","rnk":"champion","nstype":"C","rld":"2015-02-05 00:00:00.0","hr":"mordor","birthday":"2015-11-22 00:00:00.0","sex":"M"},{"firstName":"Michel","lastName":"Schuppe","tz":"767637358","mi":"705179285","clearance":"8","rnk":"unknown","nstype":"D","rld":"2029-09-26 00:00:00.0","hr":"wallmart","birthday":"1999-04-21 00:00:00.0","sex":"M"},{"firstName":"Mckayla","lastName":"Larson","tz":"294852686","mi":"351002779","clearance":"3","rnk":"rookie","nstype":"D","rld":"2023-10-17 00:00:00.0","hr":"wallmart","birthday":"2017-07-01 00:00:00.0","sex":"F"},{"firstName":"Darian","lastName":"Davis","tz":"686629056","mi":"101791730","clearance":"7","rnk":"champion","nstype":"A","rld":"2021-02-02 00:00:00.0","hr":"wallmart","birthday":"1999-06-02 00:00:00.0","sex":"F"},{"firstName":"Hailey","lastName":"Homenick","tz":"600832877","mi":"156818376","clearance":"2","rnk":"champion","nstype":"D","rld":"2017-09-12 00:00:00.0","hr":"mordor","birthday":"2000-09-11 00:00:00.0","sex":"M"},{"firstName":"Modesto","lastName":"Rippin","tz":"281035337","mi":"567116039","clearance":"1","rnk":"mega","nstype":"H","rld":"2024-04-12 00:00:00.0","hr":"gondor","birthday":"2003-01-25 00:00:00.0","sex":"F"},{"firstName":"Kobe","lastName":"Lakin","tz":"991460056","mi":"312941095","clearance":"9","rnk":"unknown","nstype":"C","rld":"2016-11-07 00:00:00.0","hr":"valhalla","birthday":"2020-12-03 00:00:00.0","sex":"M"},{"firstName":"Milo","lastName":"Smitham","tz":"277961769","mi":"860603199","clearance":"9","rnk":"rookie","nstype":"B","rld":"2018-11-13 00:00:00.0","hr":"gondor","birthday":"2006-07-05 00:00:00.0","sex":"M"},{"firstName":"Marques","lastName":"Schmeler","tz":"481929917","mi":"744511058","clearance":"1","rnk":"unknown","nstype":"D","rld":"2028-07-31 00:00:00.0","hr":"wallmart","birthday":"1998-11-04 00:00:00.0","sex":"M"},{"firstName":"Kelsie","lastName":"Zieme","tz":"584684039","mi":"510082138","clearance":"5","rnk":"unknown","nstype":"C","rld":"2023-10-14 00:00:00.0","hr":"wallmart","birthday":"1996-07-03 00:00:00.0","sex":"F"},{"firstName":"Easter","lastName":"Rippin","tz":"751894502","mi":"532153572","clearance":"2","rnk":"mega","nstype":"G","rld":"2027-08-31 00:00:00.0","hr":"wallmart","birthday":"1988-06-07 00:00:00.0","sex":"M"},{"firstName":"Marlon","lastName":"Rogahn","tz":"228824736","mi":"453284537","clearance":"0","rnk":"unknown","nstype":"F","rld":"2019-02-22 00:00:00.0","hr":"wallmart","birthday":"2000-03-04 00:00:00.0","sex":"F"},{"firstName":"Eloisa","lastName":"Douglas","tz":"462233313","mi":"895269946","clearance":"5","rnk":"champion","nstype":"G","rld":"2022-07-25 00:00:00.0","hr":"mordor","birthday":"2005-07-13 00:00:00.0","sex":"F"},{"firstName":"Jovan","lastName":"Goyette","tz":"330481474","mi":"270164259","clearance":"9","rnk":"unknown","nstype":"F","rld":"2021-09-15 00:00:00.0","hr":"gondor","birthday":"1997-01-18 00:00:00.0","sex":"M"},{"firstName":"Yasmin","lastName":"Heller","tz":"790433858","mi":"953824392","clearance":"3","rnk":"unknown","nstype":"A","rld":"2012-11-26 00:00:00.0","hr":"valhalla","birthday":"2008-09-25 00:00:00.0","sex":"F"},{"firstName":"Yasmin","lastName":"Kautzer","tz":"990176182","mi":"114961738","clearance":"6","rnk":"rookie","nstype":"E","rld":"2021-05-26 00:00:00.0","hr":"mordor","birthday":"1987-05-08 00:00:00.0","sex":"M"},{"firstName":"Loren","lastName":"Weimann","tz":"700711344","mi":"191822996","clearance":"1","rnk":"rookie","nstype":"A","rld":"2020-09-18 00:00:00.0","hr":"gondor","birthday":"2007-10-02 00:00:00.0","sex":"M"},{"firstName":"Jammie","lastName":"Davis","tz":"291618262","mi":"342397105","clearance":"7","rnk":"ultimate","nstype":"A","rld":"2027-07-14 00:00:00.0","hr":"gondor","birthday":"2013-04-22 00:00:00.0","sex":"F"},{"firstName":"Electa","lastName":"Mohr","tz":"316639269","mi":"490302274","clearance":"9","rnk":"rookie","nstype":"C","rld":"2016-09-06 00:00:00.0","hr":"mordor","birthday":"2002-02-08 00:00:00.0","sex":"M"},{"firstName":"Velda","lastName":"Pfeffer","tz":"573224417","mi":"507955398","clearance":"7","rnk":"champion","nstype":"F","rld":"2018-10-17 00:00:00.0","hr":"gondor","birthday":"1991-12-02 00:00:00.0","sex":"M"},{"firstName":"Aletha","lastName":"Hegmann","tz":"340052992","mi":"138431376","clearance":"5","rnk":"ultimate","nstype":"H","rld":"2014-10-13 00:00:00.0","hr":"wallmart","birthday":"2000-11-23 00:00:00.0","sex":"F"},{"firstName":"Cordelia","lastName":"Feeney","tz":"541432506","mi":"775180338","clearance":"10","rnk":"unknown","nstype":"C","rld":"2023-11-13 00:00:00.0","hr":"gondor","birthday":"1984-12-23 00:00:00.0","sex":"M"},{"firstName":"Pierre","lastName":"Rath","tz":"594773319","mi":"38391752","clearance":"3","rnk":"rookie","nstype":"A","rld":"2021-11-24 00:00:00.0","hr":"mordor","birthday":"2008-12-24 00:00:00.0","sex":"F"}]